{
    "imdb": {
        "raw release dates": [
            {
                "country": "Czech Republic\n",
                "date": "29 October 2014",
                "notes": "                            (internet)"
            }
        ],
        "release dates": [
            "Czech Republic::29 October 2014                            (internet)"
        ],
        "episodes": {
            "unknown season": {}
        },
        "number of episodes": 0,
        "cast": [
            {
                "name": "Tomecek, Martin"
            }
        ],
        "genres": [
            "Reality-TV"
        ],
        "runtimes": [
            "5"
        ],
        "countries": [
            "Czech Republic"
        ],
        "country codes": [
            "cz"
        ],
        "language codes": [
            "cs"
        ],
        "color info": [
            "Color"
        ],
        "languages": [
            "Czech"
        ],
        "title": "Martin Tomecek",
        "year": 2014,
        "kind": "tv series",
        "series years": "2014-",
        "akas": [
            "Martin Tomecek (Czech Republic)"
        ],
        "writer": [
            {
                "name": "Tomecek, Martin"
            }
        ],
        "distributors": [
            {
                "name": "YouTube"
            }
        ],
        "tech": {
            "runtime": [
                "5 min"
            ],
            "color": [
                "Color"
            ]
        }
    }
}