{
    "imdb": {
        "raw release dates": [
            {
                "country": "Turkey\n",
                "date": "25 October 2018"
            },
            {
                "country": "Turkey\n",
                "date": "25 October 2018",
                "notes": "                            (internet)"
            }
        ],
        "release dates": [
            "Turkey::25 October 2018",
            "Turkey::25 October 2018                            (internet)"
        ],
        "episodes": {
            "1": {
                "1": {
                    "title": "Kara Gün",
                    "kind": "episode",
                    "episode of": {
                        "title": "Kanli Dügün (TV Series 2018– )",
                        "kind": "tv series"
                    },
                    "season": 1,
                    "episode": 1,
                    "original air date": "25 Oct. 2018",
                    "year": "2018",
                    "plot": "\n  Know what this is about?\n Be the first one to add a plot.\n    "
                },
                "2": {
                    "title": "Pandora'nin Kutusu",
                    "kind": "episode",
                    "episode of": {
                        "title": "Kanli Dügün (TV Series 2018– )",
                        "kind": "tv series"
                    },
                    "season": 1,
                    "episode": 2,
                    "original air date": "25 Oct. 2018",
                    "year": "2018",
                    "plot": "\n  Know what this is about?\n Be the first one to add a plot.\n    "
                },
                "3": {
                    "title": "Serbet",
                    "kind": "episode",
                    "episode of": {
                        "title": "Kanli Dügün (TV Series 2018– )",
                        "kind": "tv series"
                    },
                    "season": 1,
                    "episode": 3,
                    "original air date": "27 Oct. 2018",
                    "year": "2018",
                    "plot": "\n  Know what this is about?\n Be the first one to add a plot.\n    "
                },
                "4": {
                    "title": "Rüyalar Gercek Olsa",
                    "kind": "episode",
                    "episode of": {
                        "title": "Kanli Dügün (TV Series 2018– )",
                        "kind": "tv series"
                    },
                    "season": 1,
                    "episode": 4,
                    "original air date": "16 Nov. 2018",
                    "year": "2018",
                    "plot": "\n  Know what this is about?\n Be the first one to add a plot.\n    "
                },
                "5": {
                    "title": "Ücüncü Göz",
                    "kind": "episode",
                    "episode of": {
                        "title": "Kanli Dügün (TV Series 2018– )",
                        "kind": "tv series"
                    },
                    "season": 1,
                    "episode": 5,
                    "original air date": "29 Nov. 2018",
                    "year": "2018",
                    "plot": "\n  Know what this is about?\n Be the first one to add a plot.\n    "
                }
            }
        },
        "number of episodes": 5,
        "cast": [
            {
                "name": "Berrin"
            },
            {
                "name": "Cemre"
            },
            {
                "name": "Sirma"
            },
            {
                "name": "Zehra"
            },
            {
                "name": "Ihsan, Ali"
            },
            {
                "name": "Suna"
            },
            {
                "name": "Melisa"
            },
            {
                "name": "Riza, Ali"
            },
            {
                "name": "Gülbahar"
            },
            {
                "name": "Murtaza"
            },
            {
                "name": "Bugra"
            },
            {
                "name": "Burcu, Burcu"
            },
            {
                "name": "Fatos"
            },
            {
                "name": "Mukaddes"
            },
            {
                "name": "Özge"
            }
        ],
        "genres": [
            "Comedy",
            "Crime",
            "Drama",
            "Mystery",
            "Thriller"
        ],
        "countries": [
            "Turkey"
        ],
        "country codes": [
            "tr"
        ],
        "language codes": [
            "tr"
        ],
        "color info": [
            "Color"
        ],
        "number of seasons": 1,
        "cover url": "https://m.media-amazon.com/images/M/MV5BNjk5MmVhMDAtODIzNC00NmFkLWFiYmQtZGJlYmY5MDk0MzBiXkEyXkFqcGdeQXVyOTU4MjAyMjg@._V1_SY150_CR11,0,101,150_.jpg",
        "languages": [
            "Turkish"
        ],
        "title": "Kanli Dügün",
        "year": 2018,
        "kind": "tv series",
        "series years": "2018-",
        "akas": [
            "Kanli Dügün (Turkey)"
        ],
        "seasons": [
            "1"
        ],
        "tech": {
            "color": [
                "Color"
            ]
        }
    }
}