{
    "imdb": {
        "raw release dates": [
            {
                "country": "UK\n",
                "date": "17 July 2017"
            }
        ],
        "release dates": [
            "UK::17 July 2017"
        ],
        "episodes": {
            "unknown season": {}
        },
        "number of episodes": 0,
        "cast": [
            {
                "name": "Torode, John"
            }
        ],
        "genres": [
            "Documentary"
        ],
        "countries": [
            "United Kingdom"
        ],
        "country codes": [
            "gb"
        ],
        "language codes": [
            "en"
        ],
        "color info": [
            "Color"
        ],
        "cover url": "https://m.media-amazon.com/images/M/MV5BZTgzNDdhZDEtODI5OC00OGYyLTkyMjEtNzdkMGQ5ZDQ1NjMzXkEyXkFqcGdeQXVyMTk5MTM3MjQ@._V1_SY150_CR106,0,101,150_.jpg",
        "languages": [
            "English"
        ],
        "title": "John Torode's Korean Food Tour",
        "year": 2017,
        "kind": "tv series",
        "series years": "2017-2017",
        "akas": [
            "John Torode's Korean Food Tour (United Kingdom)"
        ],
        "production companies": [
            {
                "name": "Denham Productions"
            }
        ],
        "tech": {
            "color": [
                "Color"
            ]
        }
    }
}