{
    "imdb": {
        "raw release dates": [
            {
                "country": "Canada\n",
                "date": "7 October 2015"
            }
        ],
        "release dates": [
            "Canada::7 October 2015"
        ],
        "episodes": {
            "1": {
                "1": {
                    "title": "Random Nonsense: Tuned In",
                    "kind": "episode",
                    "episode of": {
                        "title": "The Mike and Rob Show (TV Series 2015– )",
                        "kind": "tv series"
                    },
                    "season": 1,
                    "episode": 1,
                    "original air date": "7 Oct. 2015",
                    "year": "2015",
                    "plot": "\n    Mike and Rob talk about Winnipeg nerd news, review the latest TV shows, discuss the downfall of Jennifer Lien, and rant about the monetization of nerd culture.    "
                },
                "2": {
                    "title": "Thanks a LOT, NDT",
                    "kind": "episode",
                    "episode of": {
                        "title": "The Mike and Rob Show (TV Series 2015– )",
                        "kind": "tv series"
                    },
                    "season": 1,
                    "episode": 2,
                    "original air date": "14 Oct. 2015",
                    "year": "2015",
                    "plot": "\n    Mike, Rob and special guest host (and local cosplay enthusiast) Zoe Rose discuss the upcoming C4 Convention in Winnipeg and the new \"Cosplay is not Consent\" campaign, review the latest TV episodes and the movie The Martian, and Rob rants about Neil Degrasse Tyson's Twitter spoiler of the Matt Damon blockbuster.    "
                }
            }
        },
        "number of episodes": 2,
        "cast": [
            {
                "name": "Arsenault, Mike"
            },
            {
                "name": "Dean, Robert"
            },
            {
                "name": "Rose, Zoe"
            },
            {
                "name": "Arsenault, Mike"
            }
        ],
        "locations": [
            "Winnipeg, Manitoba, Canada"
        ],
        "genres": [
            "Comedy",
            "News",
            "Talk-Show"
        ],
        "countries": [
            "Canada"
        ],
        "country codes": [
            "ca"
        ],
        "language codes": [
            "en"
        ],
        "color info": [
            "Color"
        ],
        "aspect ratio": "16:9 HD",
        "certificates": [
            "Canada:18+"
        ],
        "number of seasons": 1,
        "languages": [
            "English"
        ],
        "title": "The Mike and Rob Show",
        "year": 2015,
        "kind": "tv series",
        "series years": "2015-",
        "akas": [
            "The Mike and Rob Show (Canada)"
        ],
        "seasons": [
            "1"
        ],
        "writer": [
            {
                "name": "Arsenault, Mike"
            },
            {
                "name": "Dean, Robert"
            },
            {
                "name": "Rumley, Clayton"
            }
        ],
        "tech": {
            "color": [
                "Color"
            ],
            "aspect ratio": [
                "16:9 HD"
            ]
        }
    }
}