{
    "imdb": {
        "raw release dates": [
            {
                "country": "USA\n",
                "date": "13 January 2011"
            },
            {
                "country": "USA\n",
                "date": "13 January 2011",
                "notes": "                            (internet)"
            }
        ],
        "release dates": [
            "USA::13 January 2011",
            "USA::13 January 2011                            (internet)"
        ],
        "episodes": {
            "7": {
                "174": {
                    "title": "Justin Meldal-Johnsen",
                    "kind": "episode",
                    "episode of": {
                        "title": "Pensado's Place (TV Series 2011– )",
                        "kind": "tv series"
                    },
                    "season": 7,
                    "episode": 174,
                    "original air date": "2 Aug. 2014",
                    "year": "2014",
                    "plot": "\n  Know what this is about?\n Be the first one to add a plot.\n    "
                },
                "175": {
                    "title": "Israel Houghton",
                    "kind": "episode",
                    "episode of": {
                        "title": "Pensado's Place (TV Series 2011– )",
                        "kind": "tv series"
                    },
                    "season": 7,
                    "episode": 175,
                    "original air date": "7 Aug. 2014",
                    "year": "2014",
                    "plot": "\n  Know what this is about?\n Be the first one to add a plot.\n    "
                },
                "176": {
                    "title": "Joe Chiccarelli",
                    "kind": "episode",
                    "episode of": {
                        "title": "Pensado's Place (TV Series 2011– )",
                        "kind": "tv series"
                    },
                    "season": 7,
                    "episode": 176,
                    "original air date": "14 Aug. 2014",
                    "year": "2014",
                    "plot": "\n  Know what this is about?\n Be the first one to add a plot.\n    "
                },
                "177": {
                    "title": "Engineer John McBride",
                    "kind": "episode",
                    "episode of": {
                        "title": "Pensado's Place (TV Series 2011– )",
                        "kind": "tv series"
                    },
                    "season": 7,
                    "episode": 177,
                    "original air date": "21 Aug. 2014",
                    "year": "2014",
                    "plot": "\n  Know what this is about?\n Be the first one to add a plot.\n    "
                },
                "178": {
                    "title": "Engineer Bob Horn",
                    "kind": "episode",
                    "episode of": {
                        "title": "Pensado's Place (TV Series 2011– )",
                        "kind": "tv series"
                    },
                    "season": 7,
                    "episode": 178,
                    "original air date": "28 Aug. 2014",
                    "year": "2014",
                    "plot": "\n  Know what this is about?\n Be the first one to add a plot.\n    "
                },
                "179": {
                    "title": "Producer and Engineer Bob Clearmountain",
                    "kind": "episode",
                    "episode of": {
                        "title": "Pensado's Place (TV Series 2011– )",
                        "kind": "tv series"
                    },
                    "season": 7,
                    "episode": 179,
                    "original air date": "4 Sep. 2014",
                    "year": "2014",
                    "plot": "\n  Know what this is about?\n Be the first one to add a plot.\n    "
                }
            },
            "1": {
                "1": {
                    "title": "Ariel Chobaz",
                    "kind": "episode",
                    "episode of": {
                        "title": "Pensado's Place (TV Series 2011– )",
                        "kind": "tv series"
                    },
                    "season": 1,
                    "episode": 1,
                    "original air date": "13 Jan. 2011",
                    "year": "2011",
                    "plot": "\n    This week is the premiere of Pensado's Place with mixing engineer Dave Pensado, his manager Herb Trawick, and engineer Zan Nakari. They are joined in studio by mixing engineer Ariel Chobaz who recently worked with Nicki Minaj on her album. In this week's Into The Lair, Dave Pensado goes over some of his favorite new compressor and eq plug-ins that he uses on his mixes. They also break down the tracks for Linkin Park's 'Waiting for the End' in this week's Playback, and the group takes questions from viewers during Corner Office.    "
                },
                "2": {
                    "title": "Jean-Marie",
                    "kind": "episode",
                    "episode of": {
                        "title": "Pensado's Place (TV Series 2011– )",
                        "kind": "tv series"
                    },
                    "season": 1,
                    "episode": 2,
                    "original air date": "20 Jan. 2011",
                    "year": "2011",
                    "plot": "\n    In 2nd episode of Pensado's Place with mixing engineer Dave Pensado, Herb Trawick, and Zan Nakari are joined by world renowned mixing engineer Jean-Marie Horvat (Michael Jackson, Justin Timberlake, TI, Reba Mcentire, Beyonce, etc.). On this week's Into The Lair, Dave goes over stereo buss compression and the difference between compressors and limiters.    "
                },
                "3": {
                    "title": "Dylan '3D' Dresdow",
                    "kind": "episode",
                    "episode of": {
                        "title": "Pensado's Place (TV Series 2011– )",
                        "kind": "tv series"
                    },
                    "season": 1,
                    "episode": 3,
                    "original air date": "27 Jan. 2011",
                    "year": "2011",
                    "plot": "\n    In the 3rd episode of Pensado's Place, Dave Pensado is joined by GRAMMY award winning mixer Dylan \"3D\" Dresdow. (Michael Jackson, Black Eyed Peas, Mariah Carey, Rihanna, Usher, The Game, Nas, Ciara, Talib Kweli, Macy Gray, Bone Thugs & Harmony, Herbie Hancock, Chris Brown, Ricky Martin and many more). On this week's Into The Lair, Dave goes talks about how he Busses tracks for mixing, and the various plug-ins he uses on those busses. The crew breaks down PitBull's newest single featuring T-Pain, \"Hey Baby (drop it to the floor)\".    "
                },
                "4": {
                    "title": "Tony Maserati",
                    "kind": "episode",
                    "episode of": {
                        "title": "Pensado's Place (TV Series 2011– )",
                        "kind": "tv series"
                    },
                    "season": 1,
                    "episode": 4,
                    "original air date": "3 Feb. 2011",
                    "year": "2011",
                    "plot": "\n    In the 4th episode of Pensado's Place, Dave Pensado is joined by legendary engineer and mixer Tony Maserati (Marc Anthony, James Brown, Mariah Carey, Destiny's Child, R. Kelly, Jennifer Lopez, Ricky Martin, Mya, Notorious B.I.G., Puff Daddy, Jessica Simpson, Tupac, Jason Mraz etc.). This week's episode was devoted entirely to the passionate discussion between Dave and Tony regarding all things mixing and engineering. New plug-ins such as the Slate Digital FG-X and the Waves C6 were covered, as well as various mixing concepts, how Will.i.am is the poster child for the ...    "
                },
                "5": {
                    "title": "Audio Production Q&A with Dave Pensado",
                    "kind": "episode",
                    "episode of": {
                        "title": "Pensado's Place (TV Series 2011– )",
                        "kind": "tv series"
                    },
                    "season": 1,
                    "episode": 5,
                    "original air date": "10 Feb. 2011",
                    "year": "2011",
                    "plot": "\n    In the 5th episode of Pensado's Place, Dave hosts an all Q&A episode with tons of great viewer questions! With Part 2/2 of the latest \"Into The Lair\", Dave takes you through some tools he used on the mix for \"Shorty is a Weirdo\" by Mr. Midwest and Ray J. Get a behind the scene look at how your favorite songs were mixed and the tools that were used by Dave!    "
                },
                "6": {
                    "title": "Manny Marroquin",
                    "kind": "episode",
                    "episode of": {
                        "title": "Pensado's Place (TV Series 2011– )",
                        "kind": "tv series"
                    },
                    "season": 1,
                    "episode": 6,
                    "original air date": "17 Feb. 2011",
                    "year": "2011",
                    "plot": "\n    In the 7th Episode of Pensado's Place, Dave is joined by Colin McDowell of McDSP PlugIns to give a special offer to all Pensado's Place viewers! In this week's Into The Lair, Dave talks about all things vocals including his favorite effects.    "
                },
                "7": {
                    "title": "Colin McDowell",
                    "kind": "episode",
                    "episode of": {
                        "title": "Pensado's Place (TV Series 2011– )",
                        "kind": "tv series"
                    },
                    "season": 1,
                    "episode": 7,
                    "original air date": "25 Feb. 2011",
                    "year": "2011",
                    "plot": "\n    In the 7th Episode of Pensado's Place, Dave is joined by Colin McDowell of McDSP PlugIns to give a special offer to all Pensado's Place viewers! In this week's Into The Lair, Dave talks about all things vocals including his favorite effects.    "
                },
                "8": {
                    "title": "Jaycen Joshua",
                    "kind": "episode",
                    "episode of": {
                        "title": "Pensado's Place (TV Series 2011– )",
                        "kind": "tv series"
                    },
                    "season": 1,
                    "episode": 8,
                    "original air date": "3 Mar. 2011",
                    "year": "2011",
                    "plot": "\n    In the 8th Episode of Pensado's Place, Dave is joined by GRAMMY award winning mixer Jaycen Joshua! This week's Into The Lair, dave interviews GRAMMY nominated engineers Andrew Wuepper and Brian \"B-Love\" Thomas about their vocal tracking methods.    "
                },
                "9": {
                    "title": "Maureen Droney",
                    "kind": "episode",
                    "episode of": {
                        "title": "Pensado's Place (TV Series 2011– )",
                        "kind": "tv series"
                    },
                    "season": 1,
                    "episode": 9,
                    "original air date": "10 Mar. 2011",
                    "year": "2011",
                    "plot": "\n    In the 9th Episode of Pensado's Place, Maureen Droney, Sr. Executive Director of the Producers & Engineers Wing of the Recording Academy joins Dave, Herb, and Zan to discuss the GRAMMY's and other aspects of NARAS (National Academy of Recording Arts and Sciences).    "
                },
                "10": {
                    "title": "James Murray",
                    "kind": "episode",
                    "episode of": {
                        "title": "Pensado's Place (TV Series 2011– )",
                        "kind": "tv series"
                    },
                    "season": 1,
                    "episode": 10,
                    "original air date": "17 Mar. 2011",
                    "year": "2011",
                    "plot": "\n    In the 10th episode of Pensado's Place, Larabee Studio's assistant engineers (Chris Galland, Drew Adams, and Jesus Garnica) join Dave to discuss how they became assistants and their day-to-day work. This week's ITL is part 1 of 2 of an in-depth walk-through of how Dave uses vocal reverbs and effects! In this week's Corner Office, Dave and the gang are answering the top 3 \"Liked\" questions via our facebook fanpage, and Producer James Murray (Alien Ant Farm, Drowning Pool, etc) joins Dave to talk about the gear he uses in The Batters Box!    "
                },
                "11": {
                    "title": "Emanuel 'E-Man' Kiriakou",
                    "kind": "episode",
                    "episode of": {
                        "title": "Pensado's Place (TV Series 2011– )",
                        "kind": "tv series"
                    },
                    "season": 1,
                    "episode": 11,
                    "original air date": "25 Mar. 2011",
                    "year": "2011",
                    "plot": "\n    In the 11th episode of Pensado's Place, Dave's guest is Producer Emanuel \"\"E-Man\"\" Kiriakou (Whitney Houston, Jordin Sparks, Selena Gomez, etc). This week's ITL is a continuation of last week's that talks all about vocal effects and various techniques.    "
                },
                "12": {
                    "title": "Dann and David Huff",
                    "kind": "episode",
                    "episode of": {
                        "title": "Pensado's Place (TV Series 2011– )",
                        "kind": "tv series"
                    },
                    "season": 1,
                    "episode": 12,
                    "original air date": "1 Apr. 2011",
                    "year": "2011",
                    "plot": "\n    In the 12th episode of Pensado's Place, Dann and David Huff join dave from Nashville via Skype to discuss Rascal Flatts, Keither Urban, and all things engineering and production! This week's ITL discusses clearing elements out of the middle to make room for vocals, as well as tricks to widen your mixes.    "
                },
                "13": {
                    "title": "Ed Cherney",
                    "kind": "episode",
                    "episode of": {
                        "title": "Pensado's Place (TV Series 2011– )",
                        "kind": "tv series"
                    },
                    "season": 1,
                    "episode": 13,
                    "original air date": "9 Apr. 2011",
                    "year": "2011",
                    "plot": "\n    In the 13th episode of Pensado's Place, engineering legend (and GRAMMY and TEC award winner) Ed Cherney stops by to chat with Dave and answer viewer questions in the \"\"Corner Office\"\". Dave and Ed then talk about their favorite gear in \"\"The Batters Box\"\", and another great \"\"Into The Lair\"\" which includes 4 distinct methods for getting instruments to sit better in the mix, as well as get more width and depth to your mixes by clearing things out of the middle!    "
                },
                "14": {
                    "title": "Mike Dean",
                    "kind": "episode",
                    "episode of": {
                        "title": "Pensado's Place (TV Series 2011– )",
                        "kind": "tv series"
                    },
                    "season": 1,
                    "episode": 14,
                    "original air date": "14 Apr. 2011",
                    "year": "2011",
                    "plot": "\n    In the 14th episode of Pensado's Place, Kanye West's engineer Mike Dean joins Dave and Herb to talk about his career, pioneering the \"Dirty South\" sound, and working with Kanye west on all of his albums! Dave and Mike then take viewer questions from the chatroom and facebook in \"The Corner Office\", followed by this week's \"Batter's Box\", where Mike answers Dave's rapid-fire questions regarding the gear he uses. This week's \"Into The Lair\" is at the end of the show, and is a continuation from last week's where Dave gives four distinct examples of how to clear out the ...    "
                },
                "15": {
                    "title": "Bruce Swedien",
                    "kind": "episode",
                    "episode of": {
                        "title": "Pensado's Place (TV Series 2011– )",
                        "kind": "tv series"
                    },
                    "season": 1,
                    "episode": 15,
                    "original air date": "21 Apr. 2011",
                    "year": "2011",
                    "plot": "\n    In the 15th episode of Pensado's Place, Engineering legend Bruce Swedien joins Dave, Herb, and Drew from his private studio in central Florida to discuss his career, engineering philosophy, and answer viewers questions. The entire episode is devoted to Bruce as he takes us on a tour of his private studio, shows us his recording set ups, and shares his engineering philosophies.    "
                },
                "16": {
                    "title": "Mark Loughman",
                    "kind": "episode",
                    "episode of": {
                        "title": "Pensado's Place (TV Series 2011– )",
                        "kind": "tv series"
                    },
                    "season": 1,
                    "episode": 16,
                    "original air date": "29 Apr. 2011",
                    "year": "2011",
                    "plot": "\n    In the 16th episode of Pensado's Place starts off with an in-depth look into the world of high-end mic pre's with BAE Audio's own Mark Loughman. They discuss the history of the venerable 1073 mic pre, and how Mark has managed to not only recreate, but improve upon this industry classic. Our guest is 3-time GRAMMY award winning mixer Phil Tan (Rihanna, Wiz Khalifa, Snoop Dogg, Enrique Iglesias, Fergie, Usher, Mariah Carey). He joins Dave and the gang via Skype to talk about his career, techniques, and favorite gear.    "
                },
                "17": {
                    "title": "Joe Baressi",
                    "kind": "episode",
                    "episode of": {
                        "title": "Pensado's Place (TV Series 2011– )",
                        "kind": "tv series"
                    },
                    "season": 1,
                    "episode": 17,
                    "original air date": "5 May 2011",
                    "year": "2011",
                    "plot": "\n    In the 17th Episode of Pensado's Place, Joe Baressi, One of the best Rock Engineer, Producer, and Mixers, joins Dave in studio to talk about his career and methodology. The episode kicks off with a follow up to Episode #16's \"\"Into The Lair\"\", featuring the amazing Esthero singing through the fantastic BAE mic preamps at Larrabee studios!    "
                },
                "18": {
                    "title": "Michael Brauer",
                    "kind": "episode",
                    "episode of": {
                        "title": "Pensado's Place (TV Series 2011– )",
                        "kind": "tv series"
                    },
                    "season": 1,
                    "episode": 18,
                    "original air date": "12 May 2011",
                    "year": "2011",
                    "plot": "\n    In the 18th episode of Penado's Place, 4-time GRAMMY winning Mixing Engineer Michael Brauer joins Dave via Skype to give a tour of his studio and outboard gear, as well as talk about his infamous \"\"Brauerize®\"\" compression technique in detail!    "
                },
                "19": {
                    "title": "All Q+A",
                    "kind": "episode",
                    "episode of": {
                        "title": "Pensado's Place (TV Series 2011– )",
                        "kind": "tv series"
                    },
                    "season": 1,
                    "episode": 19,
                    "original air date": "19 May 2011",
                    "year": "2011",
                    "plot": "\n    In this week's episode of Pensado's Place, Dave and Herb host one of Dave's past assistants, engineer Andrew Wuepper! Andrew has worked with such artists as Katy Perry, Usher, and mixed Frank Ocean's latest hit \"Novacane\". Dave and Andrew discuss engineering and mixing techniques that Andrew has used on his latest work, and take live viewer questions in \"The Corner Office\". Andrew dishes on his favorite plug-ins and hardware in \"The Batter's Box\", and in this week's \"Into The Lair\", Dave explains some of his compression techniques in the box!    "
                },
                "20": {
                    "title": "Andrew Wuepper",
                    "kind": "episode",
                    "episode of": {
                        "title": "Pensado's Place (TV Series 2011– )",
                        "kind": "tv series"
                    },
                    "season": 1,
                    "episode": 20,
                    "original air date": "27 May 2011",
                    "year": "2011",
                    "plot": "\n  Know what this is about?\n Be the first one to add a plot.\n    "
                },
                "21": {
                    "title": "Bob Hodas",
                    "kind": "episode",
                    "episode of": {
                        "title": "Pensado's Place (TV Series 2011– )",
                        "kind": "tv series"
                    },
                    "season": 1,
                    "episode": 21,
                    "original air date": "2 Jun. 2011",
                    "year": "2011",
                    "plot": "\n  Know what this is about?\n Be the first one to add a plot.\n    "
                },
                "22": {
                    "title": "Jack Joseph Puig",
                    "kind": "episode",
                    "episode of": {
                        "title": "Pensado's Place (TV Series 2011– )",
                        "kind": "tv series"
                    },
                    "season": 1,
                    "episode": 22,
                    "original air date": "10 Jun. 2011",
                    "year": "2011",
                    "plot": "\n    Dave Pensado is proud to welcome the multiple GRAMMY award winning mixer, producer, and friend - Jack Joseph Puig. To quote Steve Kurutz from AllMusic.com, Jack Joseph Puig is \"Known for his ability to merge the sounds of the past three decades to create something that is thoroughly modern...\". Jack has worked with artists such as Goo Goo Dolls, The Black Crowes, John Mayer, Weezer, Fiona Apple, Green Day, The Counting Crows, No Doubt, Klaxons, Panic at the Disco, Stone Temple Pilots, U2, and many others.    "
                },
                "23": {
                    "title": "Tricky Steward",
                    "kind": "episode",
                    "episode of": {
                        "title": "Pensado's Place (TV Series 2011– )",
                        "kind": "tv series"
                    },
                    "season": 1,
                    "episode": 23,
                    "original air date": "17 Jun. 2011",
                    "year": "2011",
                    "plot": "\n    In the 24th episode of Pensado's Place, Dave goes over Sidechain Compression techniques and Tape Saturation plug-ins in this week's \"Into The Lair\". Dave then gets put in the hot seat when he takes viewer questions from Facebook for this week's \"Batters Box\"!    "
                },
                "24": {
                    "title": "Sidechain Compression and Dave's Favorite Gear",
                    "kind": "episode",
                    "episode of": {
                        "title": "Pensado's Place (TV Series 2011– )",
                        "kind": "tv series"
                    },
                    "season": 1,
                    "episode": 24,
                    "original air date": "23 Jun. 2011",
                    "year": "2011",
                    "plot": "\n  Know what this is about?\n Be the first one to add a plot.\n    "
                },
                "25": {
                    "title": "George Saer",
                    "kind": "episode",
                    "episode of": {
                        "title": "Pensado's Place (TV Series 2011– )",
                        "kind": "tv series"
                    },
                    "season": 1,
                    "episode": 25,
                    "original air date": "30 Jun. 2011",
                    "year": "2011",
                    "plot": "\n  Know what this is about?\n Be the first one to add a plot.\n    "
                },
                "26": {
                    "title": "Alex Da Kid",
                    "kind": "episode",
                    "episode of": {
                        "title": "Pensado's Place (TV Series 2011– )",
                        "kind": "tv series"
                    },
                    "season": 1,
                    "episode": 26,
                    "original air date": "8 Jul. 2011",
                    "year": "2011",
                    "plot": "\n  Know what this is about?\n Be the first one to add a plot.\n    "
                },
                "27": {
                    "title": "Alex Da Kid Part II",
                    "kind": "episode",
                    "episode of": {
                        "title": "Pensado's Place (TV Series 2011– )",
                        "kind": "tv series"
                    },
                    "season": 1,
                    "episode": 27,
                    "original air date": "15 Jul. 2011",
                    "year": "2011",
                    "plot": "\n  Know what this is about?\n Be the first one to add a plot.\n    "
                },
                "28": {
                    "title": "Ron Fair",
                    "kind": "episode",
                    "episode of": {
                        "title": "Pensado's Place (TV Series 2011– )",
                        "kind": "tv series"
                    },
                    "season": 1,
                    "episode": 28,
                    "original air date": "21 Jul. 2011",
                    "year": "2011",
                    "plot": "\n  Know what this is about?\n Be the first one to add a plot.\n    "
                },
                "29": {
                    "title": "Jimmy Douglass",
                    "kind": "episode",
                    "episode of": {
                        "title": "Pensado's Place (TV Series 2011– )",
                        "kind": "tv series"
                    },
                    "season": 1,
                    "episode": 29,
                    "original air date": "28 Jul. 2011",
                    "year": "2011",
                    "plot": "\n  Know what this is about?\n Be the first one to add a plot.\n    "
                },
                "30": {
                    "title": "Steve Baughman",
                    "kind": "episode",
                    "episode of": {
                        "title": "Pensado's Place (TV Series 2011– )",
                        "kind": "tv series"
                    },
                    "season": 1,
                    "episode": 30,
                    "original air date": "4 Aug. 2011",
                    "year": "2011",
                    "plot": "\n  Know what this is about?\n Be the first one to add a plot.\n    "
                },
                "31": {
                    "title": "Eric Valentine",
                    "kind": "episode",
                    "episode of": {
                        "title": "Pensado's Place (TV Series 2011– )",
                        "kind": "tv series"
                    },
                    "season": 1,
                    "episode": 31,
                    "original air date": "10 Aug. 2011",
                    "year": "2011",
                    "plot": "\n  Know what this is about?\n Be the first one to add a plot.\n    "
                },
                "32": {
                    "title": "Dave Way",
                    "kind": "episode",
                    "episode of": {
                        "title": "Pensado's Place (TV Series 2011– )",
                        "kind": "tv series"
                    },
                    "season": 1,
                    "episode": 32,
                    "original air date": "18 Aug. 2011",
                    "year": "2011",
                    "plot": "\n  Know what this is about?\n Be the first one to add a plot.\n    "
                },
                "33": {
                    "title": "David Kutch",
                    "kind": "episode",
                    "episode of": {
                        "title": "Pensado's Place (TV Series 2011– )",
                        "kind": "tv series"
                    },
                    "season": 1,
                    "episode": 33,
                    "original air date": "25 Aug. 2011",
                    "year": "2011",
                    "plot": "\n  Know what this is about?\n Be the first one to add a plot.\n    "
                },
                "34": {
                    "title": "Greg Wells",
                    "kind": "episode",
                    "episode of": {
                        "title": "Pensado's Place (TV Series 2011– )",
                        "kind": "tv series"
                    },
                    "season": 1,
                    "episode": 34,
                    "original air date": "1 Sep. 2011",
                    "year": "2011",
                    "plot": "\n  Know what this is about?\n Be the first one to add a plot.\n    "
                },
                "35": {
                    "title": "All Q+A",
                    "kind": "episode",
                    "episode of": {
                        "title": "Pensado's Place (TV Series 2011– )",
                        "kind": "tv series"
                    },
                    "season": 1,
                    "episode": 35,
                    "original air date": "8 Sep. 2011",
                    "year": "2011",
                    "plot": "\n  Know what this is about?\n Be the first one to add a plot.\n    "
                },
                "36": {
                    "title": "Brian Kennedy",
                    "kind": "episode",
                    "episode of": {
                        "title": "Pensado's Place (TV Series 2011– )",
                        "kind": "tv series"
                    },
                    "season": 1,
                    "episode": 36,
                    "original air date": "15 Sep. 2011",
                    "year": "2011",
                    "plot": "\n    GRAMMY award-winning Producer Brian Kennedy, best known for writing Rihanna's \"Disturbia\" and Chris Brown's \"Forever\", joins Dave and Herb.    "
                },
                "37": {
                    "title": "Jules Standen",
                    "kind": "episode",
                    "episode of": {
                        "title": "Pensado's Place (TV Series 2011– )",
                        "kind": "tv series"
                    },
                    "season": 1,
                    "episode": 37,
                    "original air date": "20 Sep. 2011",
                    "year": "2011",
                    "plot": "\n  Know what this is about?\n Be the first one to add a plot.\n    "
                },
                "38": {
                    "title": "Peter Reardon",
                    "kind": "episode",
                    "episode of": {
                        "title": "Pensado's Place (TV Series 2011– )",
                        "kind": "tv series"
                    },
                    "season": 1,
                    "episode": 38,
                    "original air date": "29 Sep. 2011",
                    "year": "2011",
                    "plot": "\n  Know what this is about?\n Be the first one to add a plot.\n    "
                },
                "39": {
                    "title": "Joe Chiccarelli",
                    "kind": "episode",
                    "episode of": {
                        "title": "Pensado's Place (TV Series 2011– )",
                        "kind": "tv series"
                    },
                    "season": 1,
                    "episode": 39,
                    "original air date": "6 Oct. 2011",
                    "year": "2011",
                    "plot": "\n  Know what this is about?\n Be the first one to add a plot.\n    "
                },
                "40": {
                    "title": "Thomas Jouanjean",
                    "kind": "episode",
                    "episode of": {
                        "title": "Pensado's Place (TV Series 2011– )",
                        "kind": "tv series"
                    },
                    "season": 1,
                    "episode": 40,
                    "original air date": "13 Oct. 2011",
                    "year": "2011",
                    "plot": "\n  Know what this is about?\n Be the first one to add a plot.\n    "
                },
                "41": {
                    "title": "Neal Pogue",
                    "kind": "episode",
                    "episode of": {
                        "title": "Pensado's Place (TV Series 2011– )",
                        "kind": "tv series"
                    },
                    "season": 1,
                    "episode": 41,
                    "original air date": "20 Oct. 2011",
                    "year": "2011",
                    "plot": "\n  Know what this is about?\n Be the first one to add a plot.\n    "
                },
                "42": {
                    "title": "MIXFEST Preview Feat. Eric Valentine, Jean-Marie Horvat",
                    "kind": "episode",
                    "episode of": {
                        "title": "Pensado's Place (TV Series 2011– )",
                        "kind": "tv series"
                    },
                    "season": 1,
                    "episode": 42,
                    "original air date": "26 Oct. 2011",
                    "year": "2011",
                    "plot": "\n  Know what this is about?\n Be the first one to add a plot.\n    "
                },
                "43": {
                    "title": "Brent Paschke",
                    "kind": "episode",
                    "episode of": {
                        "title": "Pensado's Place (TV Series 2011– )",
                        "kind": "tv series"
                    },
                    "season": 1,
                    "episode": 43,
                    "original air date": "4 Nov. 2011",
                    "year": "2011",
                    "plot": "\n  Know what this is about?\n Be the first one to add a plot.\n    "
                },
                "44": {
                    "title": "Bobby Owsinski",
                    "kind": "episode",
                    "episode of": {
                        "title": "Pensado's Place (TV Series 2011– )",
                        "kind": "tv series"
                    },
                    "season": 1,
                    "episode": 44,
                    "original air date": "10 Nov. 2011",
                    "year": "2011",
                    "plot": "\n  Know what this is about?\n Be the first one to add a plot.\n    "
                },
                "45": {
                    "title": "Wyzard",
                    "kind": "episode",
                    "episode of": {
                        "title": "Pensado's Place (TV Series 2011– )",
                        "kind": "tv series"
                    },
                    "season": 1,
                    "episode": 45,
                    "original air date": "17 Nov. 2011",
                    "year": "2011",
                    "plot": "\n  Know what this is about?\n Be the first one to add a plot.\n    "
                },
                "46": {
                    "title": "Fabian Marasciullo",
                    "kind": "episode",
                    "episode of": {
                        "title": "Pensado's Place (TV Series 2011– )",
                        "kind": "tv series"
                    },
                    "season": 1,
                    "episode": 46,
                    "original air date": "1 Dec. 2011",
                    "year": "2011",
                    "plot": "\n  Know what this is about?\n Be the first one to add a plot.\n    "
                },
                "47": {
                    "title": "Harvey Mason, Jr.",
                    "kind": "episode",
                    "episode of": {
                        "title": "Pensado's Place (TV Series 2011– )",
                        "kind": "tv series"
                    },
                    "season": 1,
                    "episode": 47,
                    "original air date": "8 Dec. 2011",
                    "year": "2011",
                    "plot": "\n  Know what this is about?\n Be the first one to add a plot.\n    "
                },
                "48": {
                    "title": "Bret 'Epic' Mazur",
                    "kind": "episode",
                    "episode of": {
                        "title": "Pensado's Place (TV Series 2011– )",
                        "kind": "tv series"
                    },
                    "season": 1,
                    "episode": 48,
                    "original air date": "15 Dec. 2011",
                    "year": "2011",
                    "plot": "\n  Know what this is about?\n Be the first one to add a plot.\n    "
                },
                "49": {
                    "title": "Dave Aron",
                    "kind": "episode",
                    "episode of": {
                        "title": "Pensado's Place (TV Series 2011– )",
                        "kind": "tv series"
                    },
                    "season": 1,
                    "episode": 49,
                    "original air date": "22 Dec. 2011",
                    "year": "2011",
                    "plot": "\n  Know what this is about?\n Be the first one to add a plot.\n    "
                }
            },
            "2": {
                "50": {
                    "title": "Alan Meyerson",
                    "kind": "episode",
                    "episode of": {
                        "title": "Pensado's Place (TV Series 2011– )",
                        "kind": "tv series"
                    },
                    "season": 2,
                    "episode": 50,
                    "original air date": "5 Jan. 2012",
                    "year": "2012",
                    "plot": "\n  Know what this is about?\n Be the first one to add a plot.\n    "
                },
                "51": {
                    "title": "Peter Mokran",
                    "kind": "episode",
                    "episode of": {
                        "title": "Pensado's Place (TV Series 2011– )",
                        "kind": "tv series"
                    },
                    "season": 2,
                    "episode": 51,
                    "original air date": "12 Jan. 2012",
                    "year": "2012",
                    "plot": "\n  Know what this is about?\n Be the first one to add a plot.\n    "
                },
                "52": {
                    "title": "Ann Mincieli",
                    "kind": "episode",
                    "episode of": {
                        "title": "Pensado's Place (TV Series 2011– )",
                        "kind": "tv series"
                    },
                    "season": 2,
                    "episode": 52,
                    "original air date": "20 Jan. 2012",
                    "year": "2012",
                    "plot": "\n  Know what this is about?\n Be the first one to add a plot.\n    "
                },
                "53": {
                    "title": "Dave Isaac",
                    "kind": "episode",
                    "episode of": {
                        "title": "Pensado's Place (TV Series 2011– )",
                        "kind": "tv series"
                    },
                    "season": 2,
                    "episode": 53,
                    "original air date": "26 Jan. 2012",
                    "year": "2012",
                    "plot": "\n  Know what this is about?\n Be the first one to add a plot.\n    "
                },
                "54": {
                    "title": "Ken Scott",
                    "kind": "episode",
                    "episode of": {
                        "title": "Pensado's Place (TV Series 2011– )",
                        "kind": "tv series"
                    },
                    "season": 2,
                    "episode": 54,
                    "original air date": "2 Feb. 2012",
                    "year": "2012",
                    "plot": "\n  Know what this is about?\n Be the first one to add a plot.\n    "
                },
                "55": {
                    "title": "Humberto Gatica",
                    "kind": "episode",
                    "episode of": {
                        "title": "Pensado's Place (TV Series 2011– )",
                        "kind": "tv series"
                    },
                    "season": 2,
                    "episode": 55,
                    "original air date": "9 Feb. 2012",
                    "year": "2012",
                    "plot": "\n  Know what this is about?\n Be the first one to add a plot.\n    "
                },
                "56": {
                    "title": "Steve Duda",
                    "kind": "episode",
                    "episode of": {
                        "title": "Pensado's Place (TV Series 2011– )",
                        "kind": "tv series"
                    },
                    "season": 2,
                    "episode": 56,
                    "original air date": "16 Feb. 2012",
                    "year": "2012",
                    "plot": "\n  Know what this is about?\n Be the first one to add a plot.\n    "
                },
                "57": {
                    "title": "Simon Franglen",
                    "kind": "episode",
                    "episode of": {
                        "title": "Pensado's Place (TV Series 2011– )",
                        "kind": "tv series"
                    },
                    "season": 2,
                    "episode": 57,
                    "original air date": "23 Feb. 2012",
                    "year": "2012",
                    "plot": "\n  Know what this is about?\n Be the first one to add a plot.\n    "
                },
                "58": {
                    "title": "Bob Power",
                    "kind": "episode",
                    "episode of": {
                        "title": "Pensado's Place (TV Series 2011– )",
                        "kind": "tv series"
                    },
                    "season": 2,
                    "episode": 58,
                    "original air date": "1 Mar. 2012",
                    "year": "2012",
                    "plot": "\n  Know what this is about?\n Be the first one to add a plot.\n    "
                },
                "59": {
                    "title": "Jon Nettlesbey",
                    "kind": "episode",
                    "episode of": {
                        "title": "Pensado's Place (TV Series 2011– )",
                        "kind": "tv series"
                    },
                    "season": 2,
                    "episode": 59,
                    "original air date": "16 Mar. 2012",
                    "year": "2012",
                    "plot": "\n  Know what this is about?\n Be the first one to add a plot.\n    "
                },
                "60": {
                    "title": "Bob Horn",
                    "kind": "episode",
                    "episode of": {
                        "title": "Pensado's Place (TV Series 2011– )",
                        "kind": "tv series"
                    },
                    "season": 2,
                    "episode": 60,
                    "original air date": "20 Mar. 2012",
                    "year": "2012",
                    "plot": "\n  Know what this is about?\n Be the first one to add a plot.\n    "
                },
                "61": {
                    "title": "Jason Schweitzer",
                    "kind": "episode",
                    "episode of": {
                        "title": "Pensado's Place (TV Series 2011– )",
                        "kind": "tv series"
                    },
                    "season": 2,
                    "episode": 61,
                    "original air date": "29 Mar. 2012",
                    "year": "2012",
                    "plot": "\n  Know what this is about?\n Be the first one to add a plot.\n    "
                },
                "62": {
                    "title": "Kevin \"KD\" Davis",
                    "kind": "episode",
                    "episode of": {
                        "title": "Pensado's Place (TV Series 2011– )",
                        "kind": "tv series"
                    },
                    "season": 2,
                    "episode": 62,
                    "original air date": "5 Apr. 2012",
                    "year": "2012",
                    "plot": "\n  Know what this is about?\n Be the first one to add a plot.\n    "
                },
                "63": {
                    "title": "Mark \"Exit\" Goodchild",
                    "kind": "episode",
                    "episode of": {
                        "title": "Pensado's Place (TV Series 2011– )",
                        "kind": "tv series"
                    },
                    "season": 2,
                    "episode": 63,
                    "original air date": "13 Apr. 2012",
                    "year": "2012",
                    "plot": "\n  Know what this is about?\n Be the first one to add a plot.\n    "
                },
                "64": {
                    "title": "Thom Russo",
                    "kind": "episode",
                    "episode of": {
                        "title": "Pensado's Place (TV Series 2011– )",
                        "kind": "tv series"
                    },
                    "season": 2,
                    "episode": 64,
                    "original air date": "20 Apr. 2012",
                    "year": "2012",
                    "plot": "\n  Know what this is about?\n Be the first one to add a plot.\n    "
                },
                "65": {
                    "title": "Damon Elliott",
                    "kind": "episode",
                    "episode of": {
                        "title": "Pensado's Place (TV Series 2011– )",
                        "kind": "tv series"
                    },
                    "season": 2,
                    "episode": 65,
                    "original air date": "28 Apr. 2012",
                    "year": "2012",
                    "plot": "\n    In the 65th episode of Pensado's Place, Dave and Herb are joined by Producer and Writer Damon Elliott! \"Elliott has produced numerous albums and hit singles for various music artists including his mother, Dionne Warwick, as well as Destiny's Child, Beyonce, P!nk, Gwen Stefani, Jessica Simpson, Christina Aguilera, Mýa, and Macy Gray. Damon's production has earned him a Grammy and seven Grammy nominations.\"    "
                },
                "66": {
                    "title": "Ross Hogarth",
                    "kind": "episode",
                    "episode of": {
                        "title": "Pensado's Place (TV Series 2011– )",
                        "kind": "tv series"
                    },
                    "season": 2,
                    "episode": 66,
                    "original air date": "3 May 2012",
                    "year": "2012",
                    "plot": "\n    In the 66th episode of Pensado's Place, Dave and Herb are joined by 2-Time GRAMMY Award winning Engineer/Mixer/Produce Ross Hogarth! Ross has worked with such artists as Van Halen, Roger Waters, The Black Crowes, Shawn Colvin, John Mellencamp, R.E.M. and many, many more!    "
                },
                "67": {
                    "title": "Eric \"Miyerman\" Sarafin",
                    "kind": "episode",
                    "episode of": {
                        "title": "Pensado's Place (TV Series 2011– )",
                        "kind": "tv series"
                    },
                    "season": 2,
                    "episode": 67,
                    "original air date": "9 May 2012",
                    "year": "2012",
                    "plot": "\n    In the 67th episode of Pensado's Place, Dave and Herb are joined by producer, engineer, mixer, and author, Eric Sarafin aka Mixerman.    "
                },
                "68": {
                    "title": "Brian \"B-Luv\" Thomas",
                    "kind": "episode",
                    "episode of": {
                        "title": "Pensado's Place (TV Series 2011– )",
                        "kind": "tv series"
                    },
                    "season": 2,
                    "episode": 68,
                    "original air date": "17 May 2012",
                    "year": "2012",
                    "plot": "\n    Recording engineer Brian \"B-Luv\" Thomas joins Dave and Herb on the 68th episode of Pensado's Place. Brian is has tracked some of the biggest artists of the last decade including Katy Perry, Christina Aguilera, Future, The-Dream, as well as newer acts such as The Wanted and Karmin and many etc.    "
                },
                "69": {
                    "title": "Steve Slate",
                    "kind": "episode",
                    "episode of": {
                        "title": "Pensado's Place (TV Series 2011– )",
                        "kind": "tv series"
                    },
                    "season": 2,
                    "episode": 69,
                    "original air date": "23 May 2012",
                    "year": "2012",
                    "plot": "\n    Steven Slate (Producer, Engineer, and CEO of Slate Digital and Slate Pro Audio) joins Dave and Herb on the 69th episode of Pensado's Place! Steven is behind the must-have drum samples for top producers and engineers as well as the creator of innovative drum replacement software, analog emulation plugins, and now analog outboard gear. See the passion behind the awesome products and sound in this episode of Pensado's Place!    "
                },
                "70": {
                    "title": "Michael Brauer",
                    "kind": "episode",
                    "episode of": {
                        "title": "Pensado's Place (TV Series 2011– )",
                        "kind": "tv series"
                    },
                    "season": 2,
                    "episode": 70,
                    "original air date": "31 May 2012",
                    "year": "2012",
                    "plot": "\n    Mixing Engineer Michael Brauer joins Dave and Herb on the 70th episode of Pensado's Place! Skyping in from Electric Lady Studios, NY, Michael talks about his methodology when transitioning from mixing one genre to a drastically different one, along with his approach to starting a mix for a band and what to focus on. Later on Michael joins Dave in the Batter's Box and answer's viewer's questions in this week's Corner Office.    "
                },
                "71": {
                    "title": "DJ Frank E",
                    "kind": "episode",
                    "episode of": {
                        "title": "Pensado's Place (TV Series 2011– )",
                        "kind": "tv series"
                    },
                    "season": 2,
                    "episode": 71,
                    "original air date": "8 Jun. 2012",
                    "year": "2012",
                    "plot": "\n  Know what this is about?\n Be the first one to add a plot.\n    "
                },
                "72": {
                    "title": "Jay Baumgardner",
                    "kind": "episode",
                    "episode of": {
                        "title": "Pensado's Place (TV Series 2011– )",
                        "kind": "tv series"
                    },
                    "season": 2,
                    "episode": 72,
                    "original air date": "13 Jun. 2012",
                    "year": "2012",
                    "plot": "\n    In the 72nd episode of Pensado's Place, Dave and Herb are joined by Producer and Mixer, Jay Baumgardner. Jay has worked with such artists as Sevendust, Papa Roach, Godsmack, Evanescence, Three Days Grace, P.O.D., New Found Glory, Alien Ant Farm and Orgy.    "
                },
                "73": {
                    "title": "Andrew Scheps",
                    "kind": "episode",
                    "episode of": {
                        "title": "Pensado's Place (TV Series 2011– )",
                        "kind": "tv series"
                    },
                    "season": 2,
                    "episode": 73,
                    "original air date": "21 Jun. 2012",
                    "year": "2012",
                    "plot": "\n  Know what this is about?\n Be the first one to add a plot.\n    "
                },
                "74": {
                    "title": "Jay Gordon",
                    "kind": "episode",
                    "episode of": {
                        "title": "Pensado's Place (TV Series 2011– )",
                        "kind": "tv series"
                    },
                    "season": 2,
                    "episode": 74,
                    "original air date": "29 Jun. 2012",
                    "year": "2012",
                    "plot": "\n  Know what this is about?\n Be the first one to add a plot.\n    "
                },
                "75": {
                    "title": "Justin Niebank",
                    "kind": "episode",
                    "episode of": {
                        "title": "Pensado's Place (TV Series 2011– )",
                        "kind": "tv series"
                    },
                    "season": 2,
                    "episode": 75,
                    "original air date": "5 Jul. 2012",
                    "year": "2012",
                    "plot": "\n  Know what this is about?\n Be the first one to add a plot.\n    "
                },
                "76": {
                    "title": "Charlie Clouser",
                    "kind": "episode",
                    "episode of": {
                        "title": "Pensado's Place (TV Series 2011– )",
                        "kind": "tv series"
                    },
                    "season": 2,
                    "episode": 76,
                    "original air date": "26 Jul. 2012",
                    "year": "2012",
                    "plot": "\n  Know what this is about?\n Be the first one to add a plot.\n    "
                },
                "77": {
                    "title": "Marcella Araica",
                    "kind": "episode",
                    "episode of": {
                        "title": "Pensado's Place (TV Series 2011– )",
                        "kind": "tv series"
                    },
                    "season": 2,
                    "episode": 77,
                    "original air date": "2 Aug. 2012",
                    "year": "2012",
                    "plot": "\n  Know what this is about?\n Be the first one to add a plot.\n    "
                },
                "78": {
                    "title": "Kevin Augunas",
                    "kind": "episode",
                    "episode of": {
                        "title": "Pensado's Place (TV Series 2011– )",
                        "kind": "tv series"
                    },
                    "season": 2,
                    "episode": 78,
                    "original air date": "9 Aug. 2012",
                    "year": "2012",
                    "plot": "\n  Know what this is about?\n Be the first one to add a plot.\n    "
                },
                "79": {
                    "title": "Ryan Hewitt",
                    "kind": "episode",
                    "episode of": {
                        "title": "Pensado's Place (TV Series 2011– )",
                        "kind": "tv series"
                    },
                    "season": 2,
                    "episode": 79,
                    "original air date": "16 Aug. 2012",
                    "year": "2012",
                    "plot": "\n  Know what this is about?\n Be the first one to add a plot.\n    "
                },
                "80": {
                    "title": "Chris Lord-Alge",
                    "kind": "episode",
                    "episode of": {
                        "title": "Pensado's Place (TV Series 2011– )",
                        "kind": "tv series"
                    },
                    "season": 2,
                    "episode": 80,
                    "original air date": "23 Aug. 2012",
                    "year": "2012",
                    "plot": "\n  Know what this is about?\n Be the first one to add a plot.\n    "
                },
                "81": {
                    "title": "Ken Caillat",
                    "kind": "episode",
                    "episode of": {
                        "title": "Pensado's Place (TV Series 2011– )",
                        "kind": "tv series"
                    },
                    "season": 2,
                    "episode": 81,
                    "original air date": "30 Aug. 2012",
                    "year": "2012",
                    "plot": "\n  Know what this is about?\n Be the first one to add a plot.\n    "
                },
                "82": {
                    "title": "Neff-U",
                    "kind": "episode",
                    "episode of": {
                        "title": "Pensado's Place (TV Series 2011– )",
                        "kind": "tv series"
                    },
                    "season": 2,
                    "episode": 82,
                    "original air date": "5 Sep. 2012",
                    "year": "2012",
                    "plot": "\n    Neff-U talks about how important God is in his creative process, and how performing music in church helped set the foundation for working with today's top artists.    "
                },
                "83": {
                    "title": "Tom Elmhirst",
                    "kind": "episode",
                    "episode of": {
                        "title": "Pensado's Place (TV Series 2011– )",
                        "kind": "tv series"
                    },
                    "season": 2,
                    "episode": 83,
                    "original air date": "15 Sep. 2012",
                    "year": "2012",
                    "plot": "\n    Dave and Herb are joined by GRAMMY Award-winning mix engineer Tom Elmhirst! (Adele, Amy Winehouse, Mark Ronson, Hot Chip).    "
                },
                "84": {
                    "title": "Ward Hake",
                    "kind": "episode",
                    "episode of": {
                        "title": "Pensado's Place (TV Series 2011– )",
                        "kind": "tv series"
                    },
                    "season": 2,
                    "episode": 84,
                    "original air date": "28 Sep. 2012",
                    "year": "2012",
                    "plot": "\n    The trio talk about how Ward started out as a musician, songwriter, and producer, and how he carried those skill sets into his current role supervising all of the music for hit shows as Glee, Modern Family, The Simpsons, Family Guy, How I Met Your Mother, 24, and many more.    "
                },
                "85": {
                    "title": "Mike Shipley",
                    "kind": "episode",
                    "episode of": {
                        "title": "Pensado's Place (TV Series 2011– )",
                        "kind": "tv series"
                    },
                    "season": 2,
                    "episode": 85,
                    "original air date": "4 Oct. 2012",
                    "year": "2012",
                    "plot": "\n    In the 85th episode of Pensado's Place, Dave and Herb are joined by mix master Mike Shipley! Mike was in the studio or behind the board for some of the greatest albums from acts like Queen, Keith Urban, AC/DC, Def Leppard, Van Halen, Aerosmith, Tom Petty, Tim McGraw, Maroon 5, Faith Hill, Nickelback, Green Day, The Black Crowes, Alison Krauss, Papa Roach, My Chemical Romance.    "
                },
                "87": {
                    "title": "Kuk Harrell",
                    "kind": "episode",
                    "episode of": {
                        "title": "Pensado's Place (TV Series 2011– )",
                        "kind": "tv series"
                    },
                    "season": 2,
                    "episode": 87,
                    "original air date": "18 Oct. 2012",
                    "year": "2012",
                    "plot": "\n  Know what this is about?\n Be the first one to add a plot.\n    "
                }
            },
            "3": {
                "91": {
                    "title": "Dave Pensado",
                    "kind": "episode",
                    "episode of": {
                        "title": "Pensado's Place (TV Series 2011– )",
                        "kind": "tv series"
                    },
                    "season": 3,
                    "episode": 91,
                    "original air date": "15 Nov. 2012",
                    "year": "2012",
                    "plot": "\n    In the 91st episode of Pensado's Place, the tables turn as Jack Joseph Puig interviews Dave Pensado from the House of Rock in Santa Monica, CA in this special 2-part, exclusive interview! In part 1, JJP asks Dave about his past as a musician playing in bands, how he became an engineer, his work with Ron Fair and A-List artists, and much, much more!    "
                },
                "92": {
                    "title": "Dave Pensado",
                    "kind": "episode",
                    "episode of": {
                        "title": "Pensado's Place (TV Series 2011– )",
                        "kind": "tv series"
                    },
                    "season": 3,
                    "episode": 92,
                    "original air date": "22 Nov. 2012",
                    "year": "2012",
                    "plot": "\n    Part 2 of Jack Joseph Puig interviewing Dave Pensado from the House of Rock in Santa Monica, CA in this special 2-part, exclusive interview! In part 2, Dave gets put in the Batter's Box and answer's JJP's questions having to do with how Dave lays out sessions on the console, what kind of level he sends to mastering engineers, and the experience of working with some of the top artists of the last 30 years.    "
                },
                "93": {
                    "title": "Greg Wells",
                    "kind": "episode",
                    "episode of": {
                        "title": "Pensado's Place (TV Series 2011– )",
                        "kind": "tv series"
                    },
                    "season": 3,
                    "episode": 93,
                    "original air date": "30 Nov. 2012",
                    "year": "2012",
                    "plot": "\n    Producer Greg Wells returns to join Dave and Herb discuss working with Katy Perry, All American Rejects, Recording Horns, Drums, and much more on the 93rd episode of Pensado's Place! In this week's ITL, Greg and Engineer Ian MacGregor go over their drum tracking process from Greg Wells' studio.    "
                },
                "94": {
                    "title": "Raphael Saadiq",
                    "kind": "episode",
                    "episode of": {
                        "title": "Pensado's Place (TV Series 2011– )",
                        "kind": "tv series"
                    },
                    "season": 3,
                    "episode": 94,
                    "original air date": "6 Dec. 2012",
                    "year": "2012",
                    "plot": "\n    Singer, songwriter, musician, guitarist, bassist and record producer Raphael Saadiq joins Dave and Herb on the 94th episode of Pensado's Place! Dave asks Raphael about his days in Tony! Toni! Toné!, his work with Prince, his recording and album making method, his exploration into music for TV, Film, and Theater. In this week's Into The Lair, Dave discusses some ear training techniques in Part 1 of a 2-part ITL on the subject.    "
                },
                "95": {
                    "title": "Anthony Kilhoffer",
                    "kind": "episode",
                    "episode of": {
                        "title": "Pensado's Place (TV Series 2011– )",
                        "kind": "tv series"
                    },
                    "season": 3,
                    "episode": 95,
                    "original air date": "12 Dec. 2012",
                    "year": "2012",
                    "plot": "\n    3 time GRAMMY-award winning Producer and Mix Engineer Anthony Kilhoffer joins Dave and Herb on the 95th episode of Pensado's Place! The trio talk about his work on Kanye West's My Beautiful Dark Twisted Fantasy as well as Kid Cudi's Man on the Moon II. In this week's Into The Lair, Dave discusses some ear training techniques in Part 2 of a 2-part ITL on the subject.    "
                },
                "96": {
                    "title": "Charlie Wilson",
                    "kind": "episode",
                    "episode of": {
                        "title": "Pensado's Place (TV Series 2011– )",
                        "kind": "tv series"
                    },
                    "season": 3,
                    "episode": 96,
                    "original air date": "19 Dec. 2012",
                    "year": "2012",
                    "plot": "\n    Charlie Wilson, Musical Director for Rihanna and Justin Timberlake, joins Dave and Herb on the 96th episode of Pensado's Place! The trio discuss Charlie's path to, and working as, a musical director for today's top acts. In this week's Into The Lair, Dave discusses dealing with Low-End in a mix, and provides some detailed examples of his mixing process.    "
                },
                "97": {
                    "title": "Derek Ali",
                    "kind": "episode",
                    "episode of": {
                        "title": "Pensado's Place (TV Series 2011– )",
                        "kind": "tv series"
                    },
                    "season": 3,
                    "episode": 97,
                    "original air date": "4 Jan. 2013",
                    "year": "2013",
                    "plot": "\n    Mixed By Ali (Derek Ali), Mix Engineer for Kendrick Lamar's Good Kid, M.A.A.D City, joins Dave and Herb on the 97th episode of Pensado's Place! The trio discuss Derek's work on Kendrick's breakout album, as well as working with Doctor Dre, and his own mixing process. In this week's Into The Lair, Dave shows off some vocal mixing techniques he used on a recent Earth Wind & Fire track.    "
                },
                "98": {
                    "title": "Joe Barresi",
                    "kind": "episode",
                    "episode of": {
                        "title": "Pensado's Place (TV Series 2011– )",
                        "kind": "tv series"
                    },
                    "season": 3,
                    "episode": 98,
                    "original air date": "11 Jan. 2013",
                    "year": "2013",
                    "plot": "\n    Joe Barresi (Tool, Queens of the Stone Age, Coheed and Cambria, Bad Religion, Soundgarden) joins Dave and Herb on the 98th episode of Pensado's Place! The trio discuss how Joe gets a some of the best drum and guitar sounds in the business, as well as working with Soundgarden on their latest release, \"King Animal\". In this week's Into The Lair, Dave shows how to use delays without plug-ins or hardware!    "
                },
                "99": {
                    "title": "Leslie Ann Jones",
                    "kind": "episode",
                    "episode of": {
                        "title": "Pensado's Place (TV Series 2011– )",
                        "kind": "tv series"
                    },
                    "season": 3,
                    "episode": 99,
                    "original air date": "17 Jan. 2013",
                    "year": "2013",
                    "plot": "\n    GRAMMY Award-Winning Engineer Leslie Ann Jones (Herbie Hancock, Santana, and countless film scores) sits down with Dave Pensado for a special interview at Skywalker Ranch in Marin County, CA. Leslie talks about her percussionist and band leader father, Spike Jones, her path to becoming a GRAMMY-winning recording Engineer, her work at Skywalker Ranch, and her views on how to increase the role of women in the audio industry. Leslie also takes Dave out ont he scoring stage, and explains some of the technological intricacies of the facilities there.    "
                }
            },
            "4": {
                "1": {
                    "title": "Pete Lyman",
                    "kind": "episode",
                    "episode of": {
                        "title": "Pensado's Place (TV Series 2011– )",
                        "kind": "tv series"
                    },
                    "season": 4,
                    "episode": 1,
                    "original air date": "25 Jan. 2013",
                    "year": "2013",
                    "plot": "\n    Pete Lyman, Mastering Engineer and co-owner of Infrasonic Sound (http://infrasonicsound.com/) joins Dave and Herb on the 100th episode of Pensado's Place! The trio talk about the resurgence of vinyl (including what you need to know if you want to have your mix mastered for vinyl), answer common mastering questions, and talk about Pete's process when mastering. This week's \"Into The Lair\" covers mixing background vocals!    "
                },
                "3": {
                    "title": "Greg Wells: Pensado's Place NAMM 2013 Special",
                    "kind": "episode",
                    "episode of": {
                        "title": "Pensado's Place (TV Series 2011– )",
                        "kind": "tv series"
                    },
                    "season": 4,
                    "episode": 3,
                    "original air date": "26 Feb. 2013",
                    "year": "2013",
                    "plot": "\n    Producer Greg Wells joins Dave Pensado and Herb Trawick on stage at the Avid booth at NAMM 2013    "
                },
                "4": {
                    "title": "Michael Fitzpatrick: Pensado's Place NAMM 2013 Special",
                    "kind": "episode",
                    "episode of": {
                        "title": "Pensado's Place (TV Series 2011– )",
                        "kind": "tv series"
                    },
                    "season": 4,
                    "episode": 4,
                    "original air date": "26 Feb. 2013",
                    "year": "2013",
                    "plot": "\n    Michael Fitzpatrick of Fitz and The Tantrums joins Dave Pensado and Herb Trawick on stage at the Avid booth at NAMM 2013    "
                },
                "101": {
                    "title": "Chris Baseford",
                    "kind": "episode",
                    "episode of": {
                        "title": "Pensado's Place (TV Series 2011– )",
                        "kind": "tv series"
                    },
                    "season": 4,
                    "episode": 101,
                    "original air date": "7 Feb. 2013",
                    "year": "2013",
                    "plot": "\n    Chris Baseford, engineer for the likes of Rob Zombie, Tommy Lee/Motley Crue, Fuel joins Dave and Herb on the 101st episode of Pensado's Place! Chris reveals some of his favorite techniques for recording a great rock guitar sound, as well as Chris' work re-constructing mixes of classic tracks for the Rock Band and Guitar Hero franchises.    "
                },
                "102": {
                    "title": "Rupert Neve",
                    "kind": "episode",
                    "episode of": {
                        "title": "Pensado's Place (TV Series 2011– )",
                        "kind": "tv series"
                    },
                    "season": 4,
                    "episode": 102,
                    "original air date": "15 Feb. 2013",
                    "year": "2013",
                    "plot": "\n  Know what this is about?\n Be the first one to add a plot.\n    "
                },
                "103": {
                    "title": "Printz Board",
                    "kind": "episode",
                    "episode of": {
                        "title": "Pensado's Place (TV Series 2011– )",
                        "kind": "tv series"
                    },
                    "season": 4,
                    "episode": 103,
                    "original air date": "21 Feb. 2013",
                    "year": "2013",
                    "plot": "\n    Musician, producer, songwriter and musical director for The Black Eyed Peas, Printz Board joins Dave and Herb on the 103rd episode of Pensado's Place! The three talk about Printz' work with will.i.am and BEP, including the story of how they wrote \"Where Is The Love? one night before leaving to go out. Printz talks about MDing and what goes on while touring with The Black Eyed peas, as well as answers viewers questions in this weeks \"Corner Office\"!    "
                },
                "104": {
                    "title": "Ron Fair",
                    "kind": "episode",
                    "episode of": {
                        "title": "Pensado's Place (TV Series 2011– )",
                        "kind": "tv series"
                    },
                    "season": 4,
                    "episode": 104,
                    "original air date": "28 Feb. 2013",
                    "year": "2013",
                    "plot": "\n    Chief Creative Officer / EVP of Virgin Records, Ron Fair sits down with Dave and Herb on the 104th episode of Pensado's Place! The three talk about the current state of the music business, how labels are evolving, his role at virgin records, and advice for those looking to get into the music industry. This is an incredible episode you don't want to miss!    "
                },
                "105": {
                    "title": "Manny Marroquin",
                    "kind": "episode",
                    "episode of": {
                        "title": "Pensado's Place (TV Series 2011– )",
                        "kind": "tv series"
                    },
                    "season": 4,
                    "episode": 105,
                    "original air date": "7 Mar. 2013",
                    "year": "2013",
                    "plot": "\n    5 time GRAMMY award winning mix engineer, Manny Marroquin sits down with Dave and Herb on the 105th episode of Pensado's Place! The three talk about Manny's work on the new Imagine Dragon's record (produced by past guest, Alex Da Kid) the latest Bruno Mars album, Linkin Park, Alicia Keys and more! You don't want to miss these two legends talking shop!    "
                },
                "106": {
                    "title": "Tony Hoffer",
                    "kind": "episode",
                    "episode of": {
                        "title": "Pensado's Place (TV Series 2011– )",
                        "kind": "tv series"
                    },
                    "season": 4,
                    "episode": 106,
                    "original air date": "14 Mar. 2013",
                    "year": "2013",
                    "plot": "\n    Producer and Mix Engineer Tony Hoffer (Beck, M83, Silversun Pickups, Depeche Mode) sits down with Dave and Herb on the 106th episode of Pensado's Place! Dave and Tony discuss Tony's recent work on M83's \"Midnight City\", Silversun Pickups's \"Carnavas\", as well as his philosophies and methods when it comes to his mix and production work.    "
                },
                "107": {
                    "title": "Jacob Luttrell",
                    "kind": "episode",
                    "episode of": {
                        "title": "Pensado's Place (TV Series 2011– )",
                        "kind": "tv series"
                    },
                    "season": 4,
                    "episode": 107,
                    "original air date": "20 Mar. 2013",
                    "year": "2013",
                    "plot": "\n    The man behind such hits as \"Tonight (I'm Lovin' You.)\" recorded by Enrique Iglesias and \"Wild Ones,\" recorded by Flo Rida & Sia Furler - Songwriter Jacob Luttrell sits down with Dave and Herb to talk shop.    "
                },
                "108": {
                    "title": "Neal Avron",
                    "kind": "episode",
                    "episode of": {
                        "title": "Pensado's Place (TV Series 2011– )",
                        "kind": "tv series"
                    },
                    "season": 4,
                    "episode": 108,
                    "original air date": "28 Mar. 2013",
                    "year": "2013",
                    "plot": "\n    Producer and Mix Engineer Neal Avron (Everclear, Switchfoot, New Found Glory, Fall Out Boy, Yellowcard, Weezer, Sara Bareilles, Anberlin) sits down with Dave and Herb to talk shop.    "
                },
                "109": {
                    "title": "Cat Gray and Brian Teed",
                    "kind": "episode",
                    "episode of": {
                        "title": "Pensado's Place (TV Series 2011– )",
                        "kind": "tv series"
                    },
                    "season": 4,
                    "episode": 109,
                    "original air date": "4 Apr. 2013",
                    "year": "2013",
                    "plot": "\n    Musical Director for the TV Show \"Let's Make A Deal\", Cat Gray and his colleague Brian Teed take us through a day of production on the hit TV show \"Let's Make a Deal\".    "
                }
            },
            "5": {
                "110": {
                    "title": "François Tétaz",
                    "kind": "episode",
                    "episode of": {
                        "title": "Pensado's Place (TV Series 2011– )",
                        "kind": "tv series"
                    },
                    "season": 5,
                    "episode": 110,
                    "original air date": "11 Apr. 2013",
                    "year": "2013",
                    "plot": "\n    Producer and Mix Engineer François Tétaz (Gotya, Kimbra) sits down with Dave and Herb to talk shop.    "
                },
                "111": {
                    "title": "Danja",
                    "kind": "episode",
                    "episode of": {
                        "title": "Pensado's Place (TV Series 2011– )",
                        "kind": "tv series"
                    },
                    "season": 5,
                    "episode": 111,
                    "original air date": "18 Apr. 2013",
                    "year": "2013",
                    "plot": "\n    Producer joins Dave and Herb via Skype.    "
                },
                "112": {
                    "title": "Showtek",
                    "kind": "episode",
                    "episode of": {
                        "title": "Pensado's Place (TV Series 2011– )",
                        "kind": "tv series"
                    },
                    "season": 5,
                    "episode": 112,
                    "original air date": "25 Apr. 2013",
                    "year": "2013",
                    "plot": "\n    Dutch electronic act Showtek joins Dave and Herb.    "
                },
                "113": {
                    "title": "Sean 'Sully' Sullivan",
                    "kind": "episode",
                    "episode of": {
                        "title": "Pensado's Place (TV Series 2011– )",
                        "kind": "tv series"
                    },
                    "season": 5,
                    "episode": 113,
                    "original air date": "2 May 2013",
                    "year": "2013",
                    "plot": "\n    Dave and Herb are joined by Sean \"Sully\" Sullivan, Engineer and FOH Mix Engineer for acts such as Beck, Rihanna, Thom Yorke, Beastie Boys, Sheryl Crow, Norah Jones (and many more).    "
                },
                "114": {
                    "title": "Rodney 'Darkchild' Jerkins",
                    "kind": "episode",
                    "episode of": {
                        "title": "Pensado's Place (TV Series 2011– )",
                        "kind": "tv series"
                    },
                    "season": 5,
                    "episode": 114,
                    "original air date": "9 May 2013",
                    "year": "2013",
                    "plot": "\n    Songwriter, producer, and musician Rodney Jerkins (Jennifer Lopez, Michael Jackson, Justin Bieber, Whitney Houston and Britney Spears just to name a few) joins Dave and Herb to talk shop.    "
                },
                "115": {
                    "title": "Mick Guzauski",
                    "kind": "episode",
                    "episode of": {
                        "title": "Pensado's Place (TV Series 2011– )",
                        "kind": "tv series"
                    },
                    "season": 5,
                    "episode": 115,
                    "original air date": "17 May 2013",
                    "year": "2013",
                    "plot": "\n    Mix Engineer Mick Guzauski (Earth, Wind and Fire, Eric Clapton, Mariah Carey, Baby Face, Boyz to Men, Daft Punk) joins Dave and Herb to talk shop on the 115th episode of Pensado's Place. The trio talk about Mick's recent mixing and tracking work on Daft Punk's \"Random Access Memories\" as well as his work on classic albums by Mariah Carey and Eric Clapton.    "
                },
                "117": {
                    "title": "Al Schmitt",
                    "kind": "episode",
                    "episode of": {
                        "title": "Pensado's Place (TV Series 2011– )",
                        "kind": "tv series"
                    },
                    "season": 5,
                    "episode": 117,
                    "original air date": "30 May 2013",
                    "year": "2013",
                    "plot": "\n    22-time GRAMMY winning Engineer and Producer Al Schmitt joins Dave and Herb.    "
                },
                "118": {
                    "title": "Robert Duncan",
                    "kind": "episode",
                    "episode of": {
                        "title": "Pensado's Place (TV Series 2011– )",
                        "kind": "tv series"
                    },
                    "season": 5,
                    "episode": 118,
                    "original air date": "10 Jun. 2013",
                    "year": "2013",
                    "plot": "\n    Two-time Emmy-award-nominated TV and Film composer (Buffy the Vampire Slayer, The Unit, Butterfly on a Wheel and Into the Blue 2: The Reef) Robert Duncan joins Dave and Herb.    "
                },
                "119": {
                    "title": "Scotty McCreery",
                    "kind": "episode",
                    "episode of": {
                        "title": "Pensado's Place (TV Series 2011– )",
                        "kind": "tv series"
                    },
                    "season": 5,
                    "episode": 119,
                    "original air date": "20 Jun. 2013",
                    "year": "2013",
                    "plot": "\n    Scotty McCreery, country music artist and winner of American Idol season 10 gives us a backstage pass to his recent \"Weekend Roadtrip\" tour.    "
                },
                "120": {
                    "title": "Music Industry Question and Answer Session",
                    "kind": "episode",
                    "episode of": {
                        "title": "Pensado's Place (TV Series 2011– )",
                        "kind": "tv series"
                    },
                    "season": 5,
                    "episode": 120,
                    "original air date": "29 Jun. 2013",
                    "year": "2013",
                    "plot": "\n    Dave and Herb host an in-depth industry Q&A Session.    "
                },
                "121": {
                    "title": "Alex da Kid",
                    "kind": "episode",
                    "episode of": {
                        "title": "Pensado's Place (TV Series 2011– )",
                        "kind": "tv series"
                    },
                    "season": 5,
                    "episode": 121,
                    "original air date": "14 Jul. 2013",
                    "year": "2013",
                    "plot": "\n    Dave and Herb are joined by multi platinum selling music producer/songwriter and Grammy Award winning English hip-hop producer Alex da Kid.    "
                },
                "122": {
                    "title": "Dylan Dresdow",
                    "kind": "episode",
                    "episode of": {
                        "title": "Pensado's Place (TV Series 2011– )",
                        "kind": "tv series"
                    },
                    "season": 5,
                    "episode": 122,
                    "original air date": "19 Jul. 2013",
                    "year": "2013",
                    "plot": "\n    Dave and Herb are joined by GRAMMY Award winning audio engineer Dylan Dresdow.    "
                },
                "123": {
                    "title": "Harvey Mason Jr.",
                    "kind": "episode",
                    "episode of": {
                        "title": "Pensado's Place (TV Series 2011– )",
                        "kind": "tv series"
                    },
                    "season": 5,
                    "episode": 123,
                    "original air date": "27 Jul. 2013",
                    "year": "2013",
                    "plot": "\n    Dave and Herb are joined by producer and songwriter Harvey Mason Jr.    "
                },
                "124": {
                    "title": "John Feldmann",
                    "kind": "episode",
                    "episode of": {
                        "title": "Pensado's Place (TV Series 2011– )",
                        "kind": "tv series"
                    },
                    "season": 5,
                    "episode": 124,
                    "original air date": "3 Aug. 2013",
                    "year": "2013",
                    "plot": "\n    Dave and Herb are joined by producer and Goldfinger lead vocalist John Feldmann.    "
                }
            },
            "6": {
                "125": {
                    "title": "Tim Pierce",
                    "kind": "episode",
                    "episode of": {
                        "title": "Pensado's Place (TV Series 2011– )",
                        "kind": "tv series"
                    },
                    "season": 6,
                    "episode": 125,
                    "original air date": "10 Aug. 2013",
                    "year": "2013",
                    "plot": "\n    Renowned session guitar player, Tim Pierce, joins Dave and Herb.    "
                },
                "126": {
                    "title": "Tony Maserati",
                    "kind": "episode",
                    "episode of": {
                        "title": "Pensado's Place (TV Series 2011– )",
                        "kind": "tv series"
                    },
                    "season": 6,
                    "episode": 126,
                    "original air date": "18 Aug. 2013",
                    "year": "2013",
                    "plot": "\n    Dave and Herb are joined by mix engineer Tony Maserati.    "
                },
                "127": {
                    "title": "Jaycen Joshua",
                    "kind": "episode",
                    "episode of": {
                        "title": "Pensado's Place (TV Series 2011– )",
                        "kind": "tv series"
                    },
                    "season": 6,
                    "episode": 127,
                    "original air date": "22 Aug. 2013",
                    "year": "2013",
                    "plot": "\n    Dave and Herb are joined by mix engineer Jaycen Joshua.    "
                },
                "128": {
                    "title": "Mike Elizondo",
                    "kind": "episode",
                    "episode of": {
                        "title": "Pensado's Place (TV Series 2011– )",
                        "kind": "tv series"
                    },
                    "season": 6,
                    "episode": 128,
                    "original air date": "3 Sep. 2013",
                    "year": "2013",
                    "plot": "\n    Dave and Herb are joined by Producer and Songwriter Mike Elizondo.    "
                }
            },
            "-1": {
                "-1": {
                    "title": "Mike Clink",
                    "kind": "episode",
                    "episode of": {
                        "title": "Pensado's Place (TV Series 2011– )",
                        "kind": "tv series"
                    },
                    "season": -1,
                    "episode": -1,
                    "original air date": "8 Nov. 2012",
                    "year": "2012",
                    "plot": "\n  Know what this is about?\n Be the first one to add a plot.\n    "
                }
            }
        },
        "number of episodes": 132,
        "cast": [
            {
                "name": "Pensado, Dave"
            },
            {
                "name": "Trawick, Herb"
            },
            {
                "name": "Griffin, Gerald Gl"
            },
            {
                "name": "Goncz, Chongor"
            },
            {
                "name": "Adams, Drew"
            },
            {
                "name": "Thompson, Will"
            },
            {
                "name": "Maserati, Tony"
            },
            {
                "name": "Wells, Greg"
            },
            {
                "name": "Bates, Chelsea"
            },
            {
                "name": "Baseford, Chris"
            },
            {
                "name": "Chobaz, Ariel"
            },
            {
                "name": "Sarafin, Eric 'Mixerman'"
            },
            {
                "name": "Araica, Marcella"
            },
            {
                "name": "Augunas, Kevin"
            },
            {
                "name": "Baumgardner, Jay"
            },
            {
                "name": "Brauer, Michael"
            },
            {
                "name": "Caillat, Ken"
            },
            {
                "name": "Clink, Mike"
            },
            {
                "name": "Clouser, Charlie"
            },
            {
                "name": "Elliott, Damon"
            },
            {
                "name": "Elmhirst, Tom"
            },
            {
                "name": "Feemster, Ron"
            },
            {
                "name": "Franks, Justin"
            },
            {
                "name": "Gordon, Jay"
            },
            {
                "name": "Hake, Ward"
            },
            {
                "name": "Harrell, Kuk"
            },
            {
                "name": "Hewitt, Ryan"
            },
            {
                "name": "Hogarth, Ross"
            },
            {
                "name": "Kilhoffer, Anthony"
            },
            {
                "name": "Lord-Alge, Chris"
            },
            {
                "name": "Niebank, Justin"
            },
            {
                "name": "Puig, Jack Joseph"
            },
            {
                "name": "Puig, Jack Joseph"
            },
            {
                "name": "Saadiq, Raphael"
            },
            {
                "name": "Scheps, Andrew"
            },
            {
                "name": "Shipley, Mike"
            },
            {
                "name": "Slate, Steven"
            },
            {
                "name": "Taylor, Damian"
            },
            {
                "name": "Wilson, Charlie"
            },
            {
                "name": "Ali, Derek"
            },
            {
                "name": "Avron, Neal"
            },
            {
                "name": "Barresi, Joe"
            },
            {
                "name": "Basefor, Chris"
            },
            {
                "name": "Braun, Jayme"
            },
            {
                "name": "da Kid, Alex"
            },
            {
                "name": "Dresdow, Dylan"
            },
            {
                "name": "Duncan, Robert"
            },
            {
                "name": "Elizondo, Mike"
            },
            {
                "name": "Fair, Ron"
            },
            {
                "name": "Feldmann, John"
            }
        ],
        "locations": [
            "Santa Monica, California, USA"
        ],
        "genres": [
            "Music",
            "Talk-Show"
        ],
        "countries": [
            "United States"
        ],
        "country codes": [
            "us"
        ],
        "language codes": [
            "en"
        ],
        "color info": [
            "Color"
        ],
        "number of seasons": 7,
        "rating": 9.0,
        "votes": 24,
        "cover url": "https://m.media-amazon.com/images/M/MV5BY2EzNzQ2OGMtNjg3ZS00NDAxLWJmNDYtYjViYjY3MWQ4Mjk5XkEyXkFqcGdeQXVyMjMxODgwNTI@._V1_SY150_CR1,0,101,150_.jpg",
        "budget": "$20,000 (estimated)",
        "plot outline": "Top mixing engineer Dave Pensado talks all things music and audio in his weekly show, Pensado's Place. Dave gives you insights into his career and teaches you how to get that \"platinum record\" sound for your own mixes through tutorials and interviews.",
        "languages": [
            "English"
        ],
        "title": "Pensado's Place",
        "year": 2011,
        "kind": "tv series",
        "series years": "2011-",
        "akas": [
            "Pensado's Place (United States)"
        ],
        "seasons": [
            "1",
            "2",
            "3",
            "4",
            "5",
            "6",
            "7"
        ],
        "production companies": [
            {
                "name": "Penwick Media"
            }
        ],
        "distributors": [
            {
                "name": "YouTube"
            }
        ],
        "plot": [
            "Top mixing engineer Dave Pensado talks all things music and audio in his weekly show, _Pensado's Place_ (qv). Dave gives you insights into his career and teaches you how to get that \"platinum record\" sound for your own mixes through tutorials and interviews.::Will Thompson"
        ],
        "tech": {
            "color": [
                "Color"
            ]
        },
        "demographics": {
            "imdb users": {
                "votes": 24,
                "rating": 9.0
            },
            "aged 18 29": {
                "votes": 8,
                "rating": 6.2
            },
            "aged 30 44": {
                "votes": 10,
                "rating": 7.6
            },
            "aged 45 plus": {
                "votes": 1,
                "rating": 10.0
            },
            "males": {
                "votes": 18,
                "rating": 7.1
            },
            "males aged 18 29": {
                "votes": 8,
                "rating": 6.2
            },
            "males aged 30 44": {
                "votes": 9,
                "rating": 7.5
            },
            "females": {
                "votes": 2,
                "rating": 10.0
            },
            "females aged 30 44": {
                "votes": 1,
                "rating": 10.0
            },
            "females aged 45 plus": {
                "votes": 1,
                "rating": 10.0
            },
            "top 1000 voters": {
                "votes": 1,
                "rating": 4.0
            },
            "us users": {
                "votes": 9,
                "rating": 4.5
            },
            "non us users": {
                "votes": 8,
                "rating": 9.2
            }
        },
        "number of votes": {
            "10": 18,
            "9": 3,
            "8": 0,
            "7": 0,
            "6": 0,
            "5": 0,
            "4": 1,
            "3": 1,
            "2": 0,
            "1": 1
        },
        "arithmetic mean": 9.0,
        "median": 1
    }
}