{
    "imdb": {
        "raw release dates": [
            {
                "country": "USA\n",
                "date": "17 June 2013"
            }
        ],
        "release dates": [
            "USA::17 June 2013"
        ],
        "episodes": {
            "unknown season": {}
        },
        "number of episodes": 0,
        "cast": [
            {
                "name": "Bobritsky, Max"
            },
            {
                "name": "Lauer, Ian"
            },
            {
                "name": "Smiler, Jack"
            }
        ],
        "locations": [
            "Los Angeles, California, USA"
        ],
        "genres": [
            "Reality-TV"
        ],
        "runtimes": [
            "26"
        ],
        "countries": [
            "United States"
        ],
        "country codes": [
            "us"
        ],
        "language codes": [
            "en"
        ],
        "color info": [
            "Color"
        ],
        "aspect ratio": "4K DCP",
        "sound mix": [
            "Stereo"
        ],
        "cover url": "https://m.media-amazon.com/images/M/MV5BNDQ3MmNiM2UtOWQ1Zi00Mjg4LWJiN2UtYmVlMWQ3NzA5YTY2XkEyXkFqcGdeQXVyMjIzMTQ2NDY@._V1_SY150_CR7,0,101,150_.jpg",
        "budget": "$150,000 (estimated)",
        "languages": [
            "English"
        ],
        "title": "Cooking: California Style",
        "year": 2013,
        "kind": "tv series",
        "series years": "2013-",
        "akas": [
            "Cooking: California Style (United States)"
        ],
        "writer": [
            {
                "name": "Bobritsky, Max"
            },
            {
                "name": "Davies, Len"
            },
            {
                "name": "Smiler, Jack"
            }
        ],
        "production companies": [
            {
                "name": "Spectrum Multimedia Hollywood"
            }
        ],
        "distributors": [
            {
                "name": "Ladies First Distribution"
            }
        ],
        "plot": [
            "Join Jack Smiler and Max Bobritsky as they show you how to cook California Style.::Len Davies"
        ],
        "tech": {
            "runtime": [
                "26 min"
            ],
            "sound mix": [
                "Stereo"
            ],
            "color": [
                "Color"
            ],
            "aspect ratio": [
                "4K DCP"
            ]
        }
    }
}