{
    "imdb": {
        "raw release dates": [
            {
                "country": "USA\n",
                "date": "2 November 2013"
            }
        ],
        "release dates": [
            "USA::2 November 2013"
        ],
        "episodes": {
            "unknown season": {}
        },
        "number of episodes": 0,
        "cast": [
            {
                "name": "Cascio, Tony"
            },
            {
                "name": "Garza, Gilbert"
            },
            {
                "name": "Heredia, Robert"
            },
            {
                "name": "Hundert, Rena"
            },
            {
                "name": "Jordan, Hallie"
            },
            {
                "name": "Klein, Jesse"
            },
            {
                "name": "Lochan, Shannel"
            },
            {
                "name": "Lopez, Galicia Vaca"
            },
            {
                "name": "Moreno, Gina"
            },
            {
                "name": "Sturges, Brian"
            }
        ],
        "genres": [
            "Comedy"
        ],
        "countries": [
            "United States"
        ],
        "country codes": [
            "us"
        ],
        "language codes": [
            "en"
        ],
        "color info": [
            "Color"
        ],
        "original air date": "02 Nov 2013 (USA)",
        "languages": [
            "English"
        ],
        "title": "Gina's World",
        "year": 2013,
        "kind": "tv mini series",
        "series years": "2013-",
        "akas": [
            "Gina's World (United States)"
        ],
        "writer": [
            {
                "name": "Klein, Jesse Noah"
            },
            {
                "name": "Moreno, Gina"
            },
            {
                "name": "Whalen, Nicolle M."
            }
        ],
        "director": [
            {
                "name": "Whalen, Nicolle M."
            }
        ],
        "plot": [
            "A variety show with a multitude of comedic sketches.::Paul Isakson"
        ],
        "tech": {
            "color": [
                "Color"
            ]
        }
    }
}