{
    "imdb": {
        "raw release dates": [
            {
                "country": "USA\n",
                "date": "1 May 2015"
            }
        ],
        "release dates": [
            "USA::1 May 2015"
        ],
        "episodes": {
            "1": {
                "1": {
                    "title": "The One with Shang Forbes in a Barbershop",
                    "kind": "episode",
                    "episode of": {
                        "title": "Kamikaze Comedy (TV Series 2015– )",
                        "kind": "tv series"
                    },
                    "season": 1,
                    "episode": 1,
                    "original air date": "1 May 2015",
                    "year": "2015",
                    "plot": "\n    Our Kamikaze Comedy team crashes a local barbershop and its no-holds-barred as comedian Shang Forbes takes the mic.    "
                },
                "2": {
                    "title": "The One with Adam Hunter on a Driving Range",
                    "kind": "episode",
                    "episode of": {
                        "title": "Kamikaze Comedy (TV Series 2015– )",
                        "kind": "tv series"
                    },
                    "season": 1,
                    "episode": 2,
                    "original air date": "8 May 2015",
                    "year": "2015",
                    "plot": "\n    Our Kamikaze Comedy team crashes a driving range as comedian Adam Hunter takes the mic...and ducks for cover.    "
                },
                "3": {
                    "title": "The One Where the Guys Comedy Bomb the Hood",
                    "kind": "episode",
                    "episode of": {
                        "title": "Kamikaze Comedy (TV Series 2015– )",
                        "kind": "tv series"
                    },
                    "season": 1,
                    "episode": 3,
                    "original air date": "23 May 2015",
                    "year": "2015",
                    "plot": "\n    Our Kamikaze Comedy team hits the park as Adam Hunter and Brad Williams pull out all the stops to win over a tough crowd hanging at a park bench. It's power, through comedy.    "
                },
                "4": {
                    "title": "The One Where the Guys Visit a Retirement Home",
                    "kind": "episode",
                    "episode of": {
                        "title": "Kamikaze Comedy (TV Series 2015– )",
                        "kind": "tv series"
                    },
                    "season": 1,
                    "episode": 4,
                    "original air date": "29 May 2015",
                    "year": "2015",
                    "plot": "\n    Our Kamikaze Comedy team of Adam Hunter and Jay Davis pose as motivational speakers to give these retirees inspiration through comedy.    "
                },
                "5": {
                    "title": "The One Where the Guys Hit the Beach",
                    "kind": "episode",
                    "episode of": {
                        "title": "Kamikaze Comedy (TV Series 2015– )",
                        "kind": "tv series"
                    },
                    "season": 1,
                    "episode": 5,
                    "original air date": "5 Jun. 2015",
                    "year": "2015",
                    "plot": "\n    Our Kamikaze Comedy team ambushes a group of sunbathers on the beach to give them some summertime laughs.    "
                },
                "6": {
                    "title": "The One with KT Tatara in a Hair Salon",
                    "kind": "episode",
                    "episode of": {
                        "title": "Kamikaze Comedy (TV Series 2015– )",
                        "kind": "tv series"
                    },
                    "season": 1,
                    "episode": 6,
                    "original air date": "12 Jun. 2015",
                    "year": "2015",
                    "plot": "\n    Our Kamikaze Comedy team ambushes a local hair salon.    "
                },
                "7": {
                    "title": "The Marriage Proposal",
                    "kind": "episode",
                    "episode of": {
                        "title": "Kamikaze Comedy (TV Series 2015– )",
                        "kind": "tv series"
                    },
                    "season": 1,
                    "episode": 7,
                    "original air date": "19 Jun. 2015",
                    "year": "2015",
                    "plot": "\n    Our Kamikaze Comedy team hits the pier as comedian Adam Hunter attempts a marriage proposal on stage that erupts into a wave of comedy.    "
                },
                "8": {
                    "title": "The One Where the Team Revisits the Retirement Home",
                    "kind": "episode",
                    "episode of": {
                        "title": "Kamikaze Comedy (TV Series 2015– )",
                        "kind": "tv series"
                    },
                    "season": 1,
                    "episode": 8,
                    "original air date": "26 Jun. 2015",
                    "year": "2015",
                    "plot": "\n    Our Kamikaze Comedy team is back for more, as comedians Theo Von and Brody Stevens dish up laughs for these retirees.    "
                },
                "9": {
                    "title": "The One Where the Team Crashes a Pole Dancing Class",
                    "kind": "episode",
                    "episode of": {
                        "title": "Kamikaze Comedy (TV Series 2015– )",
                        "kind": "tv series"
                    },
                    "season": 1,
                    "episode": 9,
                    "original air date": "3 Jul. 2015",
                    "year": "2015",
                    "plot": "\n    Comedians April Macie and Shayma Tash crash a pole dancing class to learn some moves and teach these girls a thing or two about comedy.    "
                },
                "10": {
                    "title": "The One Where Adam Tells Jokes to a Kid",
                    "kind": "episode",
                    "episode of": {
                        "title": "Kamikaze Comedy (TV Series 2015– )",
                        "kind": "tv series"
                    },
                    "season": 1,
                    "episode": 10,
                    "original air date": "17 Jul. 2015",
                    "year": "2015",
                    "plot": "\n    This week, the Kamikaze Comedy team hits the 3rd Street Promenade as comedian Adam Hunter tells pint sized jokes to a kid.    "
                },
                "11": {
                    "title": "The One Where the Big Guy Crashes a Party",
                    "kind": "episode",
                    "episode of": {
                        "title": "Kamikaze Comedy (TV Series 2015– )",
                        "kind": "tv series"
                    },
                    "season": 1,
                    "episode": 11,
                    "original air date": "24 Jul. 2015",
                    "year": "2015",
                    "plot": "\n    The Kamikaze Comedy team bring out the very big laughs as comedian Ramsey Moore crashes a bachelorette party.    "
                }
            }
        },
        "number of episodes": 11,
        "cast": [
            {
                "name": "Hunter, Adam"
            },
            {
                "name": "Davis, Jay"
            },
            {
                "name": "Forbes, Shang"
            },
            {
                "name": "Macie, April"
            },
            {
                "name": "Macy, April"
            },
            {
                "name": "Moore, Ramsey"
            },
            {
                "name": "Stevens, Brody"
            },
            {
                "name": "Stuart, Jason"
            },
            {
                "name": "Tash, Shayma"
            },
            {
                "name": "Tatara, K.T."
            },
            {
                "name": "Von, Theo"
            },
            {
                "name": "Williams, Brad"
            }
        ],
        "genres": [
            "Comedy"
        ],
        "countries": [
            "United States"
        ],
        "country codes": [
            "us"
        ],
        "language codes": [
            "en"
        ],
        "color info": [
            "Color"
        ],
        "number of seasons": 1,
        "languages": [
            "English"
        ],
        "title": "Kamikaze Comedy",
        "year": 2015,
        "kind": "tv series",
        "series years": "2015-",
        "akas": [
            "Kamikaze Comedy (United States)"
        ],
        "seasons": [
            "1"
        ],
        "production companies": [
            {
                "name": "GeekNation"
            },
            {
                "name": "Jamie Kennedy Entertainment"
            }
        ],
        "distributors": [
            {
                "name": "GeekNation"
            }
        ],
        "plot": [
            "It's the photo-bombing of comedy. Watch as a variety of comedians literally kamikaze every day people in every day situations with live stand up comedy. You never know what these comedians will say and how people will react."
        ],
        "tech": {
            "color": [
                "Color"
            ]
        }
    }
}