{
    "imdb": {
        "raw release dates": [
            {
                "country": "Brazil\n",
                "date": "10 November 2015"
            }
        ],
        "release dates": [
            "Brazil::10 November 2015"
        ],
        "episodes": {
            "1": {
                "1": {
                    "title": "A Promessa",
                    "kind": "episode",
                    "episode of": {
                        "title": "Tronquinho e Pão de Queijo (TV Series 2015– )",
                        "kind": "tv series"
                    },
                    "season": 1,
                    "episode": 1,
                    "original air date": "10 Nov. 2015",
                    "year": "2015",
                    "plot": "\n  Know what this is about?\n Be the first one to add a plot.\n    "
                },
                "2": {
                    "title": "Eu Genio da Lampada",
                    "kind": "episode",
                    "episode of": {
                        "title": "Tronquinho e Pão de Queijo (TV Series 2015– )",
                        "kind": "tv series"
                    },
                    "season": 1,
                    "episode": 2,
                    "original air date": "10 Nov. 2015",
                    "year": "2015",
                    "plot": "\n  Know what this is about?\n Be the first one to add a plot.\n    "
                },
                "3": {
                    "title": "A Pescaria",
                    "kind": "episode",
                    "episode of": {
                        "title": "Tronquinho e Pão de Queijo (TV Series 2015– )",
                        "kind": "tv series"
                    },
                    "season": 1,
                    "episode": 3,
                    "original air date": "10 Nov. 2015",
                    "year": "2015",
                    "plot": "\n  Know what this is about?\n Be the first one to add a plot.\n    "
                },
                "4": {
                    "title": "Apocalipse Maiaca",
                    "kind": "episode",
                    "episode of": {
                        "title": "Tronquinho e Pão de Queijo (TV Series 2015– )",
                        "kind": "tv series"
                    },
                    "season": 1,
                    "episode": 4,
                    "original air date": "10 Nov. 2015",
                    "year": "2015",
                    "plot": "\n  Know what this is about?\n Be the first one to add a plot.\n    "
                },
                "5": {
                    "title": "Cabra Macho",
                    "kind": "episode",
                    "episode of": {
                        "title": "Tronquinho e Pão de Queijo (TV Series 2015– )",
                        "kind": "tv series"
                    },
                    "season": 1,
                    "episode": 5,
                    "original air date": "10 Nov. 2015",
                    "year": "2015",
                    "plot": "\n  Know what this is about?\n Be the first one to add a plot.\n    "
                },
                "6": {
                    "title": "Os Saltimbancos",
                    "kind": "episode",
                    "episode of": {
                        "title": "Tronquinho e Pão de Queijo (TV Series 2015– )",
                        "kind": "tv series"
                    },
                    "season": 1,
                    "episode": 6,
                    "original air date": "10 Nov. 2015",
                    "year": "2015",
                    "plot": "\n  Know what this is about?\n Be the first one to add a plot.\n    "
                },
                "7": {
                    "title": "O Gigante Cegueta",
                    "kind": "episode",
                    "episode of": {
                        "title": "Tronquinho e Pão de Queijo (TV Series 2015– )",
                        "kind": "tv series"
                    },
                    "season": 1,
                    "episode": 7,
                    "original air date": "10 Nov. 2015",
                    "year": "2015",
                    "plot": "\n  Know what this is about?\n Be the first one to add a plot.\n    "
                },
                "8": {
                    "title": "O Astronauta",
                    "kind": "episode",
                    "episode of": {
                        "title": "Tronquinho e Pão de Queijo (TV Series 2015– )",
                        "kind": "tv series"
                    },
                    "season": 1,
                    "episode": 8,
                    "original air date": "10 Nov. 2015",
                    "year": "2015",
                    "plot": "\n  Know what this is about?\n Be the first one to add a plot.\n    "
                },
                "9": {
                    "title": "A Maudição do Faraó",
                    "kind": "episode",
                    "episode of": {
                        "title": "Tronquinho e Pão de Queijo (TV Series 2015– )",
                        "kind": "tv series"
                    },
                    "season": 1,
                    "episode": 9,
                    "original air date": "10 Nov. 2015",
                    "year": "2015",
                    "plot": "\n  Know what this is about?\n Be the first one to add a plot.\n    "
                },
                "10": {
                    "title": "Concurso de Bolos",
                    "kind": "episode",
                    "episode of": {
                        "title": "Tronquinho e Pão de Queijo (TV Series 2015– )",
                        "kind": "tv series"
                    },
                    "season": 1,
                    "episode": 10,
                    "original air date": "10 Nov. 2015",
                    "year": "2015",
                    "plot": "\n  Know what this is about?\n Be the first one to add a plot.\n    "
                },
                "11": {
                    "title": "Belércules",
                    "kind": "episode",
                    "episode of": {
                        "title": "Tronquinho e Pão de Queijo (TV Series 2015– )",
                        "kind": "tv series"
                    },
                    "season": 1,
                    "episode": 11,
                    "original air date": "10 Nov. 2015",
                    "year": "2015",
                    "plot": "\n  Know what this is about?\n Be the first one to add a plot.\n    "
                },
                "12": {
                    "title": "Cavaleiro Fantasma",
                    "kind": "episode",
                    "episode of": {
                        "title": "Tronquinho e Pão de Queijo (TV Series 2015– )",
                        "kind": "tv series"
                    },
                    "season": 1,
                    "episode": 12,
                    "original air date": "10 Nov. 2015",
                    "year": "2015",
                    "plot": "\n  Know what this is about?\n Be the first one to add a plot.\n    "
                },
                "13": {
                    "title": "O Faquir",
                    "kind": "episode",
                    "episode of": {
                        "title": "Tronquinho e Pão de Queijo (TV Series 2015– )",
                        "kind": "tv series"
                    },
                    "season": 1,
                    "episode": 13,
                    "original air date": "10 Nov. 2015",
                    "year": "2015",
                    "plot": "\n  Know what this is about?\n Be the first one to add a plot.\n    "
                },
                "14": {
                    "title": "Guerra Bolonhesa",
                    "kind": "episode",
                    "episode of": {
                        "title": "Tronquinho e Pão de Queijo (TV Series 2015– )",
                        "kind": "tv series"
                    },
                    "season": 1,
                    "episode": 14,
                    "original air date": "10 Nov. 2015",
                    "year": "2015",
                    "plot": "\n  Know what this is about?\n Be the first one to add a plot.\n    "
                },
                "15": {
                    "title": "Palhaço Sem Graça",
                    "kind": "episode",
                    "episode of": {
                        "title": "Tronquinho e Pão de Queijo (TV Series 2015– )",
                        "kind": "tv series"
                    },
                    "season": 1,
                    "episode": 15,
                    "original air date": "10 Nov. 2015",
                    "year": "2015",
                    "plot": "\n  Know what this is about?\n Be the first one to add a plot.\n    "
                },
                "16": {
                    "title": "A Espada do Rei",
                    "kind": "episode",
                    "episode of": {
                        "title": "Tronquinho e Pão de Queijo (TV Series 2015– )",
                        "kind": "tv series"
                    },
                    "season": 1,
                    "episode": 16,
                    "original air date": "10 Nov. 2015",
                    "year": "2015",
                    "plot": "\n  Know what this is about?\n Be the first one to add a plot.\n    "
                },
                "17": {
                    "title": "O Sono Real",
                    "kind": "episode",
                    "episode of": {
                        "title": "Tronquinho e Pão de Queijo (TV Series 2015– )",
                        "kind": "tv series"
                    },
                    "season": 1,
                    "episode": 17,
                    "original air date": "10 Nov. 2015",
                    "year": "2015",
                    "plot": "\n  Know what this is about?\n Be the first one to add a plot.\n    "
                },
                "18": {
                    "title": "The Vozerio",
                    "kind": "episode",
                    "episode of": {
                        "title": "Tronquinho e Pão de Queijo (TV Series 2015– )",
                        "kind": "tv series"
                    },
                    "season": 1,
                    "episode": 18,
                    "original air date": "10 Nov. 2015",
                    "year": "2015",
                    "plot": "\n  Know what this is about?\n Be the first one to add a plot.\n    "
                },
                "19": {
                    "title": "Peste dos Ratos",
                    "kind": "episode",
                    "episode of": {
                        "title": "Tronquinho e Pão de Queijo (TV Series 2015– )",
                        "kind": "tv series"
                    },
                    "season": 1,
                    "episode": 19,
                    "original air date": "10 Nov. 2015",
                    "year": "2015",
                    "plot": "\n  Know what this is about?\n Be the first one to add a plot.\n    "
                },
                "20": {
                    "title": "Zeleus do Trovão",
                    "kind": "episode",
                    "episode of": {
                        "title": "Tronquinho e Pão de Queijo (TV Series 2015– )",
                        "kind": "tv series"
                    },
                    "season": 1,
                    "episode": 20,
                    "original air date": "10 Nov. 2015",
                    "year": "2015",
                    "plot": "\n  Know what this is about?\n Be the first one to add a plot.\n    "
                },
                "21": {
                    "title": "O Sábio da Montanha",
                    "kind": "episode",
                    "episode of": {
                        "title": "Tronquinho e Pão de Queijo (TV Series 2015– )",
                        "kind": "tv series"
                    },
                    "season": 1,
                    "episode": 21,
                    "original air date": "10 Nov. 2015",
                    "year": "2015",
                    "plot": "\n  Know what this is about?\n Be the first one to add a plot.\n    "
                },
                "22": {
                    "title": "O Mímico",
                    "kind": "episode",
                    "episode of": {
                        "title": "Tronquinho e Pão de Queijo (TV Series 2015– )",
                        "kind": "tv series"
                    },
                    "season": 1,
                    "episode": 22,
                    "original air date": "10 Nov. 2015",
                    "year": "2015",
                    "plot": "\n  Know what this is about?\n Be the first one to add a plot.\n    "
                },
                "23": {
                    "title": "Leo de Asparta",
                    "kind": "episode",
                    "episode of": {
                        "title": "Tronquinho e Pão de Queijo (TV Series 2015– )",
                        "kind": "tv series"
                    },
                    "season": 1,
                    "episode": 23,
                    "original air date": "10 Nov. 2015",
                    "year": "2015",
                    "plot": "\n  Know what this is about?\n Be the first one to add a plot.\n    "
                },
                "24": {
                    "title": "Vaca Amarela",
                    "kind": "episode",
                    "episode of": {
                        "title": "Tronquinho e Pão de Queijo (TV Series 2015– )",
                        "kind": "tv series"
                    },
                    "season": 1,
                    "episode": 24,
                    "original air date": "10 Nov. 2015",
                    "year": "2015",
                    "plot": "\n  Know what this is about?\n Be the first one to add a plot.\n    "
                },
                "25": {
                    "title": "Floresta do Tempo Perdido",
                    "kind": "episode",
                    "episode of": {
                        "title": "Tronquinho e Pão de Queijo (TV Series 2015– )",
                        "kind": "tv series"
                    },
                    "season": 1,
                    "episode": 25,
                    "original air date": "10 Nov. 2015",
                    "year": "2015",
                    "plot": "\n  Know what this is about?\n Be the first one to add a plot.\n    "
                },
                "26": {
                    "title": "Com a Bruxa Atrás da Orelha",
                    "kind": "episode",
                    "episode of": {
                        "title": "Tronquinho e Pão de Queijo (TV Series 2015– )",
                        "kind": "tv series"
                    },
                    "season": 1,
                    "episode": 26,
                    "original air date": "10 Nov. 2015",
                    "year": "2015",
                    "plot": "\n  Know what this is about?\n Be the first one to add a plot.\n    "
                }
            }
        },
        "number of episodes": 26,
        "genres": [
            "Animation"
        ],
        "countries": [
            "Brazil"
        ],
        "country codes": [
            "br"
        ],
        "language codes": [
            "pt"
        ],
        "color info": [
            "Color"
        ],
        "number of seasons": 1,
        "cover url": "https://m.media-amazon.com/images/M/MV5BNDVlOTc2NTUtMWEzYS00ZGRkLWI2MGEtNWRkMTk0YmY3MWNkXkEyXkFqcGdeQXVyMTQ5NzYyNzM@._V1_SY150_CR25,0,101,150_.jpg",
        "budget": "$1,000,000 (estimated)",
        "languages": [
            "Portuguese"
        ],
        "title": "Tronquinho e Pão de Queijo",
        "year": 2015,
        "kind": "tv series",
        "series years": "2015-",
        "akas": [
            "Tronquinho e Pão de Queijo (Brazil)"
        ],
        "seasons": [
            "1"
        ],
        "writer": [
            {
                "name": "Colombo, Gustavo"
            },
            {
                "name": "Gava, Rodrigo"
            },
            {
                "name": "Pimentel, Vitor"
            }
        ],
        "production companies": [
            {
                "name": "Gava Produções Digitais"
            }
        ],
        "distributors": [
            {
                "name": "Gloob"
            }
        ],
        "tech": {
            "color": [
                "Color"
            ]
        }
    }
}